{"Troops":[{"troopId":3,"tribeId":100025,"id":88,"y":2642,"x":594,"groupId":4000200},{"troopId":2,"tribeId":100002,"id":158,"y":3185,"x":1268,"groupId":206019},{"troopId":3,"tribeId":100061,"id":115,"y":458,"x":1750,"groupId":4000719},{"troopId":3,"tribeId":100002,"id":297,"y":2977,"x":1490,"groupId":206303},{"troopId":3,"tribeId":100061,"id":64,"y":607,"x":1833,"groupId":4001203},{"troopId":2,"tribeId":100061,"id":114,"y":650,"x":1846,"groupId":4000719},{"troopId":8,"tribeId":100054,"id":125,"y":2489,"x":1366,"groupId":206497},{"troopId":2,"tribeId":1000066,"id":1076,"y":732,"x":1485,"groupId":205353},{"troopId":6,"tribeId":100054,"id":528,"y":2864,"x":1200,"groupId":200505},{"troopId":2,"tribeId":100061,"id":149,"y":5801,"x":1133,"groupId":4000742},{"troopId":3,"tribeId":100025,"id":261,"y":2804,"x":1536,"groupId":203528},{"troopId":9,"tribeId":100061,"id":137,"y":883,"x":1712,"groupId":4001130},{"troopId":2,"tribeId":100061,"id":62,"y":806,"x":1933,"groupId":4001203},{"troopId":3,"tribeId":100061,"id":27,"y":839,"x":2003,"groupId":4001525},{"troopId":2,"tribeId":100025,"id":229,"y":3653,"x":373,"groupId":203480},{"troopId":2,"tribeId":100038,"id":235,"y":3955,"x":1843,"groupId":201550},{"troopId":4,"tribeId":100061,"id":148,"y":1051,"x":1593,"groupId":4000560},{"troopId":4,"tribeId":100061,"id":527,"y":1004,"x":1575,"groupId":206599},{"troopId":9,"tribeId":100061,"id":623,"y":3022,"x":1287,"groupId":206244},{"troopId":8,"tribeId":100061,"id":624,"y":3466,"x":1250,"groupId":206244},{"troopId":2,"tribeId":100061,"id":23,"y":1040,"x":1715,"groupId":4001571},{"troopId":3,"tribeId":100048,"id":133,"y":4148,"x":1549,"groupId":4000016},{"troopId":2,"tribeId":100061,"id":28,"y":4074,"x":1600,"groupId":4001561},{"troopId":2,"tribeId":100249,"id":123,"y":1138,"x":1196,"groupId":202591},{"troopId":2,"tribeId":100328,"id":1055,"y":1105,"x":1572,"groupId":203886},{"troopId":2,"tribeId":100328,"id":537,"y":1161,"x":1621,"groupId":4000288},{"troopId":2,"tribeId":100048,"id":132,"y":4429,"x":1408,"groupId":4000016},{"troopId":2,"tribeId":100190,"id":293,"y":1121,"x":1909,"groupId":4000036},{"troopId":2,"tribeId":100190,"id":210,"y":1111,"x":2145,"groupId":4000729},{"troopId":2,"tribeId":100205,"id":135,"y":1713,"x":2117,"groupId":4000711},{"troopId":2,"tribeId":100328,"id":301,"y":1258,"x":1680,"groupId":4000265},{"troopId":2,"tribeId":100328,"id":690,"y":1258,"x":1667,"groupId":204167},{"troopId":2,"tribeId":100328,"id":52,"y":1258,"x":1686,"groupId":4000854},{"troopId":2,"tribeId":100328,"id":674,"y":1258,"x":1713,"groupId":203335},{"troopId":4,"tribeId":100002,"id":240,"y":2751,"x":1610,"groupId":206260},{"troopId":2,"tribeId":100061,"id":136,"y":4078,"x":1600,"groupId":4001001},{"troopId":3,"tribeId":100025,"id":233,"y":3208,"x":526,"groupId":203480},{"troopId":2,"tribeId":100048,"id":124,"y":4899,"x":1173,"groupId":202781},{"troopId":2,"tribeId":100190,"id":513,"y":1274,"x":2227,"groupId":201789},{"troopId":2,"tribeId":100054,"id":182,"y":2891,"x":1366,"groupId":205623},{"troopId":2,"tribeId":100134,"id":275,"y":1320,"x":1680,"groupId":206866},{"troopId":2,"tribeId":100061,"id":147,"y":1329,"x":2183,"groupId":4000560},{"troopId":2,"tribeId":100061,"id":526,"y":1397,"x":2174,"groupId":206599},{"troopId":2,"tribeId":100293,"id":755,"y":1346,"x":2116,"groupId":206774},{"troopId":2,"tribeId":100190,"id":456,"y":1378,"x":2279,"groupId":4000314},{"troopId":4,"tribeId":100025,"id":101,"y":3550,"x":697,"groupId":4000781},{"troopId":4,"tribeId":100190,"id":362,"y":3860,"x":2507,"groupId":206850},{"troopId":2,"tribeId":100002,"id":361,"y":2751,"x":1530,"groupId":202512},{"troopId":2,"tribeId":100190,"id":134,"y":3829,"x":2653,"groupId":4000816},{"troopId":3,"tribeId":100025,"id":143,"y":2642,"x":582,"groupId":206399},{"troopId":2,"tribeId":100134,"id":556,"y":1545,"x":1293,"groupId":205913},{"troopId":3,"tribeId":100134,"id":928,"y":1587,"x":1244,"groupId":201508},{"troopId":2,"tribeId":100190,"id":24,"y":3206,"x":2406,"groupId":4001141},{"troopId":3,"tribeId":100134,"id":1236,"y":1570,"x":1947,"groupId":203003},{"troopId":2,"tribeId":100134,"id":1235,"y":1571,"x":1947,"groupId":203003},{"troopId":7,"tribeId":100134,"id":855,"y":1599,"x":1935,"groupId":206591},{"troopId":9,"tribeId":100134,"id":857,"y":1578,"x":1934,"groupId":206591},{"troopId":10,"tribeId":100134,"id":858,"y":1579,"x":1925,"groupId":206591},{"troopId":2,"tribeId":100134,"id":414,"y":1587,"x":1963,"groupId":4000435},{"troopId":4,"tribeId":100134,"id":1237,"y":1570,"x":1947,"groupId":203003},{"troopId":11,"tribeId":100134,"id":859,"y":1580,"x":1926,"groupId":206591},{"troopId":8,"tribeId":100134,"id":856,"y":1599,"x":1935,"groupId":206591},{"troopId":2,"tribeId":100205,"id":246,"y":1580,"x":2243,"groupId":4000105},{"troopId":2,"tribeId":100134,"id":929,"y":1630,"x":1261,"groupId":201508},{"troopId":2,"tribeId":100054,"id":404,"y":1637,"x":1391,"groupId":203170},{"troopId":3,"tribeId":100134,"id":206,"y":1619,"x":1344,"groupId":4000408},{"troopId":5,"tribeId":100134,"id":853,"y":1602,"x":1922,"groupId":206591},{"troopId":2,"tribeId":100134,"id":850,"y":1604,"x":1921,"groupId":206591},{"troopId":6,"tribeId":100134,"id":854,"y":1601,"x":1922,"groupId":206591},{"troopId":4,"tribeId":100134,"id":852,"y":1603,"x":1921,"groupId":206591},{"troopId":3,"tribeId":100134,"id":851,"y":1604,"x":1921,"groupId":206591},{"troopId":5,"tribeId":100054,"id":197,"y":2506,"x":1540,"groupId":206262},{"troopId":2,"tribeId":100025,"id":203,"y":2639,"x":583,"groupId":4001265},{"troopId":5,"tribeId":100205,"id":834,"y":1626,"x":2146,"groupId":204056},{"troopId":2,"tribeId":100375,"id":39,"y":1755,"x":1587,"groupId":206704},{"troopId":6,"tribeId":100205,"id":835,"y":1625,"x":2146,"groupId":204056},{"troopId":6,"tribeId":100025,"id":445,"y":3543,"x":379,"groupId":204411},{"troopId":2,"tribeId":100061,"id":721,"y":1766,"x":1287,"groupId":203726},{"troopId":2,"tribeId":100054,"id":67,"y":1725,"x":1373,"groupId":4000716},{"troopId":2,"tribeId":100048,"id":341,"y":3810,"x":1718,"groupId":200705},{"troopId":2,"tribeId":100153,"id":121,"y":1779,"x":1537,"groupId":4001063},{"troopId":2,"tribeId":100190,"id":731,"y":3456,"x":2517,"groupId":202725},{"troopId":2,"tribeId":0,"id":178,"y":3282,"x":455,"groupId":4000675},{"troopId":2,"tribeId":100134,"id":331,"y":4850,"x":1730,"groupId":4000625},{"troopId":4,"tribeId":100205,"id":833,"y":1770,"x":2146,"groupId":204056},{"troopId":3,"tribeId":100205,"id":832,"y":1771,"x":2219,"groupId":204056},{"troopId":7,"tribeId":100205,"id":836,"y":1766,"x":2217,"groupId":204056},{"troopId":2,"tribeId":100205,"id":831,"y":1772,"x":2220,"groupId":204056},{"troopId":4,"tribeId":100213,"id":304,"y":3604,"x":350,"groupId":4000201},{"troopId":2,"tribeId":100061,"id":26,"y":1710,"x":2398,"groupId":4001525},{"troopId":2,"tribeId":100249,"id":180,"y":3448,"x":651,"groupId":4000346},{"troopId":2,"tribeId":100184,"id":102,"y":3738,"x":2678,"groupId":204282},{"troopId":3,"tribeId":100054,"id":441,"y":1843,"x":1068,"groupId":206809},{"troopId":2,"tribeId":100061,"id":155,"y":1822,"x":1162,"groupId":4000700},{"troopId":2,"tribeId":100061,"id":198,"y":3417,"x":1111,"groupId":206678},{"troopId":2,"tribeId":100054,"id":139,"y":1847,"x":1289,"groupId":4000188},{"troopId":3,"tribeId":100054,"id":199,"y":1804,"x":1796,"groupId":206262},{"troopId":2,"tribeId":100054,"id":332,"y":1847,"x":1702,"groupId":201562},{"troopId":2,"tribeId":100061,"id":504,"y":1821,"x":1918,"groupId":201683},{"troopId":2,"tribeId":100190,"id":81,"y":1877,"x":2202,"groupId":4000982},{"troopId":3,"tribeId":100002,"id":399,"y":3114,"x":1662,"groupId":201451},{"troopId":2,"tribeId":100190,"id":176,"y":4346,"x":2270,"groupId":4000725},{"troopId":2,"tribeId":100061,"id":257,"y":2802,"x":2304,"groupId":4001061},{"troopId":4,"tribeId":100054,"id":403,"y":1955,"x":1232,"groupId":203170},{"troopId":3,"tribeId":100002,"id":764,"y":1921,"x":1702,"groupId":200985},{"troopId":2,"tribeId":100205,"id":409,"y":1928,"x":2174,"groupId":202952},{"troopId":2,"tribeId":100061,"id":691,"y":1941,"x":2280,"groupId":200979},{"troopId":2,"tribeId":100058,"id":718,"y":2088,"x":734,"groupId":205461},{"troopId":4,"tribeId":100025,"id":442,"y":3550,"x":376,"groupId":204411},{"troopId":2,"tribeId":100054,"id":680,"y":2020,"x":1122,"groupId":203641},{"troopId":3,"tribeId":100054,"id":402,"y":2094,"x":1293,"groupId":203170},{"troopId":2,"tribeId":100002,"id":774,"y":2020,"x":1824,"groupId":201166},{"troopId":4,"tribeId":100216,"id":368,"y":2056,"x":2622,"groupId":206325},{"troopId":2,"tribeId":100002,"id":100,"y":2540,"x":1646,"groupId":4001029},{"troopId":4,"tribeId":100054,"id":43,"y":2116,"x":949,"groupId":4001226},{"troopId":2,"tribeId":100249,"id":604,"y":2122,"x":955,"groupId":204156},{"troopId":2,"tribeId":100002,"id":116,"y":2754,"x":1815,"groupId":206762},{"troopId":2,"tribeId":100061,"id":486,"y":3878,"x":1518,"groupId":200953},{"troopId":3,"tribeId":100002,"id":336,"y":2188,"x":1619,"groupId":206286},{"troopId":4,"tribeId":100002,"id":259,"y":2751,"x":1687,"groupId":201537},{"troopId":4,"tribeId":100002,"id":260,"y":2176,"x":1745,"groupId":206386},{"troopId":5,"tribeId":100002,"id":258,"y":2720,"x":1675,"groupId":201537},{"troopId":7,"tribeId":100025,"id":194,"y":5004,"x":1679,"groupId":4000950},{"troopId":4,"tribeId":100054,"id":196,"y":2506,"x":1540,"groupId":206262},{"troopId":2,"tribeId":100190,"id":411,"y":2110,"x":2575,"groupId":203022},{"troopId":3,"tribeId":100249,"id":741,"y":2207,"x":800,"groupId":206228},{"troopId":3,"tribeId":100190,"id":232,"y":3617,"x":3352,"groupId":4000130},{"troopId":2,"tribeId":100061,"id":379,"y":2249,"x":1145,"groupId":202787},{"troopId":4,"tribeId":100054,"id":129,"y":2270,"x":1293,"groupId":4000129},{"troopId":2,"tribeId":100061,"id":243,"y":2220,"x":1385,"groupId":206644},{"troopId":4,"tribeId":100054,"id":315,"y":3929,"x":1700,"groupId":201014},{"troopId":2,"tribeId":100190,"id":208,"y":2466,"x":2331,"groupId":4000520},{"troopId":2,"tribeId":100280,"id":236,"y":5328,"x":1503,"groupId":206147},{"troopId":3,"tribeId":100054,"id":576,"y":3628,"x":937,"groupId":203094},{"troopId":2,"tribeId":100375,"id":241,"y":2278,"x":2582,"groupId":4001084},{"troopId":3,"tribeId":100054,"id":98,"y":3140,"x":1293,"groupId":4000121},{"troopId":2,"tribeId":100190,"id":181,"y":3262,"x":2381,"groupId":202638},{"troopId":8,"tribeId":100054,"id":106,"y":2507,"x":1366,"groupId":4000193},{"troopId":2,"tribeId":100002,"id":371,"y":2354,"x":1619,"groupId":4000146},{"troopId":5,"tribeId":100002,"id":635,"y":2392,"x":1672,"groupId":200919},{"troopId":4,"tribeId":100002,"id":634,"y":2398,"x":1669,"groupId":200919},{"troopId":2,"tribeId":100205,"id":291,"y":2396,"x":2408,"groupId":203323},{"troopId":2,"tribeId":100249,"id":213,"y":2495,"x":656,"groupId":204764},{"troopId":4,"tribeId":100249,"id":214,"y":2495,"x":656,"groupId":204764},{"troopId":2,"tribeId":100002,"id":175,"y":2751,"x":1606,"groupId":205022},{"troopId":2,"tribeId":100025,"id":95,"y":3649,"x":371,"groupId":4000916},{"troopId":2,"tribeId":100025,"id":170,"y":3672,"x":383,"groupId":201679},{"troopId":4,"tribeId":100054,"id":438,"y":2468,"x":1266,"groupId":206809},{"troopId":6,"tribeId":100134,"id":694,"y":2457,"x":1244,"groupId":206627},{"troopId":2,"tribeId":100054,"id":96,"y":2463,"x":1366,"groupId":4000121},{"troopId":2,"tribeId":100002,"id":173,"y":2866,"x":1643,"groupId":206624},{"troopId":4,"tribeId":100054,"id":330,"y":2489,"x":1523,"groupId":201562},{"troopId":3,"tribeId":100002,"id":633,"y":2439,"x":1648,"groupId":200919},{"troopId":2,"tribeId":100002,"id":632,"y":2518,"x":1635,"groupId":206658},{"troopId":5,"tribeId":100002,"id":646,"y":2443,"x":1675,"groupId":201729},{"troopId":3,"tribeId":100061,"id":324,"y":3956,"x":2201,"groupId":206668},{"troopId":2,"tribeId":100134,"id":215,"y":2462,"x":1725,"groupId":206263},{"troopId":2,"tribeId":100213,"id":59,"y":3604,"x":493,"groupId":206084},{"troopId":2,"tribeId":100375,"id":321,"y":2474,"x":2599,"groupId":4000639},{"troopId":2,"tribeId":100013,"id":722,"y":2948,"x":2012,"groupId":200159},{"troopId":3,"tribeId":100013,"id":723,"y":3074,"x":1949,"groupId":200159},{"troopId":3,"tribeId":100375,"id":322,"y":2410,"x":2602,"groupId":4000639},{"troopId":8,"tribeId":100002,"id":462,"y":4252,"x":2328,"groupId":4000171},{"troopId":2,"tribeId":0,"id":507,"y":2537,"x":742,"groupId":203548},{"troopId":3,"tribeId":100061,"id":1034,"y":2559,"x":996,"groupId":201116},{"troopId":2,"tribeId":100280,"id":107,"y":5328,"x":1503,"groupId":4001013},{"troopId":3,"tribeId":100054,"id":541,"y":2531,"x":982,"groupId":201249},{"troopId":3,"tribeId":100054,"id":343,"y":2517,"x":982,"groupId":200865},{"troopId":3,"tribeId":100054,"id":742,"y":2559,"x":1277,"groupId":204809},{"troopId":5,"tribeId":100054,"id":743,"y":2559,"x":1277,"groupId":204809},{"troopId":3,"tribeId":100054,"id":42,"y":2582,"x":1234,"groupId":4001226},{"troopId":5,"tribeId":100054,"id":573,"y":2512,"x":1362,"groupId":203094},{"troopId":7,"tribeId":100054,"id":344,"y":2525,"x":1366,"groupId":200865},{"troopId":2,"tribeId":100054,"id":540,"y":2557,"x":1309,"groupId":201249},{"troopId":2,"tribeId":100002,"id":290,"y":2519,"x":1563,"groupId":204473},{"troopId":3,"tribeId":100002,"id":289,"y":2537,"x":1554,"groupId":204473},{"troopId":3,"tribeId":100002,"id":99,"y":2557,"x":1637,"groupId":4001029},{"troopId":3,"tribeId":100002,"id":79,"y":2572,"x":2017,"groupId":4000737},{"troopId":2,"tribeId":100025,"id":68,"y":2641,"x":593,"groupId":4000906},{"troopId":2,"tribeId":100054,"id":152,"y":4701,"x":1668,"groupId":203696},{"troopId":5,"tribeId":100025,"id":447,"y":2641,"x":582,"groupId":204411},{"troopId":4,"tribeId":100025,"id":74,"y":3125,"x":484,"groupId":4000906},{"troopId":2,"tribeId":100025,"id":339,"y":2649,"x":578,"groupId":4000690},{"troopId":4,"tribeId":100025,"id":327,"y":2646,"x":596,"groupId":202129},{"troopId":2,"tribeId":100002,"id":94,"y":2936,"x":1532,"groupId":4000974},{"troopId":3,"tribeId":100061,"id":325,"y":3035,"x":2524,"groupId":203701},{"troopId":3,"tribeId":100025,"id":329,"y":3688,"x":391,"groupId":202129},{"troopId":4,"tribeId":100025,"id":396,"y":2644,"x":595,"groupId":201855},{"troopId":3,"tribeId":100025,"id":799,"y":2650,"x":598,"groupId":202298},{"troopId":2,"tribeId":100025,"id":397,"y":3688,"x":391,"groupId":201855},{"troopId":5,"tribeId":100025,"id":110,"y":2624,"x":573,"groupId":4000777},{"troopId":2,"tribeId":100048,"id":252,"y":4826,"x":1210,"groupId":201660},{"troopId":3,"tribeId":100048,"id":253,"y":4513,"x":1366,"groupId":201660},{"troopId":7,"tribeId":100025,"id":326,"y":2649,"x":597,"groupId":202129},{"troopId":4,"tribeId":100025,"id":557,"y":2647,"x":596,"groupId":203260},{"troopId":7,"tribeId":100002,"id":470,"y":4352,"x":2424,"groupId":4000171},{"troopId":4,"tribeId":100025,"id":806,"y":2659,"x":602,"groupId":206402},{"troopId":7,"tribeId":100002,"id":543,"y":3537,"x":1548,"groupId":201194},{"troopId":3,"tribeId":100061,"id":265,"y":3749,"x":1610,"groupId":205715},{"troopId":4,"tribeId":100054,"id":172,"y":2661,"x":1201,"groupId":205957},{"troopId":10,"tribeId":100054,"id":50,"y":2631,"x":1366,"groupId":4000964},{"troopId":2,"tribeId":100054,"id":370,"y":2651,"x":1484,"groupId":200927},{"troopId":3,"tribeId":100002,"id":34,"y":2642,"x":1708,"groupId":4001395},{"troopId":2,"tribeId":100025,"id":35,"y":3651,"x":372,"groupId":4000925},{"troopId":3,"tribeId":100375,"id":549,"y":2646,"x":2535,"groupId":4000220},{"troopId":3,"tribeId":100190,"id":356,"y":2682,"x":2539,"groupId":206850},{"troopId":2,"tribeId":100167,"id":567,"y":2652,"x":2954,"groupId":206376},{"troopId":4,"tribeId":100025,"id":49,"y":3632,"x":363,"groupId":4001044},{"troopId":2,"tribeId":100025,"id":97,"y":3728,"x":411,"groupId":4000781},{"troopId":2,"tribeId":100061,"id":679,"y":3958,"x":2201,"groupId":201106},{"troopId":4,"tribeId":100048,"id":254,"y":4290,"x":1478,"groupId":201660},{"troopId":2,"tribeId":100061,"id":255,"y":3685,"x":1726,"groupId":4000335},{"troopId":5,"tribeId":100048,"id":245,"y":4136,"x":1555,"groupId":200128},{"troopId":2,"tribeId":100025,"id":179,"y":3555,"x":324,"groupId":206356},{"troopId":8,"tribeId":100002,"id":238,"y":2751,"x":1687,"groupId":206260},{"troopId":9,"tribeId":100002,"id":237,"y":2705,"x":1675,"groupId":206260},{"troopId":5,"tribeId":100002,"id":239,"y":2705,"x":1602,"groupId":206260},{"troopId":2,"tribeId":100002,"id":230,"y":2762,"x":1655,"groupId":200045},{"troopId":3,"tribeId":100002,"id":159,"y":3190,"x":1266,"groupId":206019},{"troopId":3,"tribeId":100002,"id":160,"y":2796,"x":1636,"groupId":4000073},{"troopId":2,"tribeId":100002,"id":55,"y":2705,"x":1736,"groupId":4000472},{"troopId":2,"tribeId":100190,"id":446,"y":3438,"x":2499,"groupId":203337},{"troopId":2,"tribeId":100048,"id":244,"y":4322,"x":1462,"groupId":200128},{"troopId":2,"tribeId":100002,"id":156,"y":2735,"x":2051,"groupId":4000073},{"troopId":2,"tribeId":100205,"id":390,"y":2756,"x":2371,"groupId":201958},{"troopId":4,"tribeId":100025,"id":191,"y":5052,"x":1609,"groupId":4000950},{"troopId":6,"tribeId":100025,"id":193,"y":5044,"x":1667,"groupId":4000950},{"troopId":2,"tribeId":100375,"id":53,"y":2767,"x":2586,"groupId":4001400},{"troopId":4,"tribeId":100025,"id":474,"y":2886,"x":365,"groupId":204035},{"troopId":3,"tribeId":100025,"id":867,"y":3579,"x":361,"groupId":206294},{"troopId":2,"tribeId":100025,"id":866,"y":3579,"x":361,"groupId":206294},{"troopId":4,"tribeId":100054,"id":91,"y":2899,"x":774,"groupId":4001143},{"troopId":6,"tribeId":100054,"id":126,"y":2932,"x":1187,"groupId":206497},{"troopId":2,"tribeId":100054,"id":575,"y":2837,"x":982,"groupId":203094},{"troopId":2,"tribeId":100190,"id":346,"y":4492,"x":2447,"groupId":4000808},{"troopId":4,"tribeId":100025,"id":109,"y":3158,"x":501,"groupId":4000004},{"troopId":9,"tribeId":100054,"id":529,"y":2864,"x":1200,"groupId":200505},{"troopId":2,"tribeId":1000020,"id":234,"y":3263,"x":1631,"groupId":201609},{"troopId":3,"tribeId":100054,"id":530,"y":2897,"x":1366,"groupId":200505},{"troopId":7,"tribeId":100061,"id":621,"y":2879,"x":1314,"groupId":206244},{"troopId":2,"tribeId":100002,"id":583,"y":2865,"x":1591,"groupId":200004},{"troopId":3,"tribeId":100002,"id":582,"y":2840,"x":1579,"groupId":200004},{"troopId":6,"tribeId":100002,"id":727,"y":2896,"x":1637,"groupId":200006},{"troopId":3,"tribeId":100002,"id":728,"y":3202,"x":1721,"groupId":206712},{"troopId":4,"tribeId":100190,"id":348,"y":4427,"x":2491,"groupId":4000808},{"troopId":8,"tribeId":100025,"id":195,"y":5064,"x":1692,"groupId":4000950},{"troopId":5,"tribeId":100025,"id":192,"y":5052,"x":1635,"groupId":4000950},{"troopId":3,"tribeId":100025,"id":306,"y":3702,"x":398,"groupId":201545},{"troopId":2,"tribeId":100249,"id":54,"y":2998,"x":772,"groupId":4001482},{"troopId":4,"tribeId":100054,"id":482,"y":2946,"x":799,"groupId":206794},{"troopId":3,"tribeId":100054,"id":312,"y":2901,"x":1186,"groupId":201014},{"troopId":5,"tribeId":100061,"id":620,"y":2987,"x":1264,"groupId":206244},{"troopId":10,"tribeId":100061,"id":622,"y":2981,"x":1315,"groupId":206244},{"troopId":3,"tribeId":100002,"id":166,"y":2928,"x":1485,"groupId":200052},{"troopId":3,"tribeId":100002,"id":93,"y":2905,"x":1516,"groupId":4000974},{"troopId":5,"tribeId":100002,"id":157,"y":2912,"x":1694,"groupId":4000073},{"troopId":2,"tribeId":100002,"id":539,"y":2911,"x":1681,"groupId":201656},{"troopId":3,"tribeId":100002,"id":1147,"y":2931,"x":1658,"groupId":201543},{"troopId":15,"tribeId":100002,"id":463,"y":4252,"x":2288,"groupId":4000171},{"troopId":16,"tribeId":100002,"id":464,"y":4470,"x":2503,"groupId":4000171},{"troopId":2,"tribeId":100213,"id":466,"y":3640,"x":367,"groupId":202219},{"troopId":2,"tribeId":100054,"id":314,"y":3490,"x":1481,"groupId":201014},{"troopId":3,"tribeId":100375,"id":307,"y":2931,"x":2560,"groupId":4000998},{"troopId":2,"tribeId":100375,"id":762,"y":2932,"x":2658,"groupId":4000198},{"troopId":2,"tribeId":100375,"id":17,"y":2981,"x":2723,"groupId":4001602},{"troopId":2,"tribeId":100167,"id":891,"y":3055,"x":304,"groupId":205809},{"troopId":3,"tribeId":100249,"id":380,"y":3054,"x":652,"groupId":205641},{"troopId":2,"tribeId":100304,"id":167,"y":3510,"x":2796,"groupId":205678},{"troopId":2,"tribeId":100375,"id":177,"y":3085,"x":2702,"groupId":4001313},{"troopId":6,"tribeId":100025,"id":127,"y":3631,"x":362,"groupId":4000107},{"troopId":2,"tribeId":100054,"id":531,"y":3029,"x":1282,"groupId":200505},{"troopId":7,"tribeId":100054,"id":532,"y":3029,"x":1282,"groupId":200505},{"troopId":9,"tribeId":100054,"id":51,"y":3013,"x":1223,"groupId":4000964},{"troopId":4,"tribeId":100061,"id":619,"y":3036,"x":1250,"groupId":206244},{"troopId":5,"tribeId":100054,"id":313,"y":3078,"x":1275,"groupId":201014},{"troopId":2,"tribeId":100025,"id":382,"y":5711,"x":1654,"groupId":4000409},{"troopId":10,"tribeId":100054,"id":533,"y":3033,"x":1311,"groupId":200505},{"troopId":2,"tribeId":100002,"id":565,"y":3098,"x":1473,"groupId":206107},{"troopId":3,"tribeId":100002,"id":1368,"y":3063,"x":1465,"groupId":201273},{"troopId":2,"tribeId":100002,"id":1369,"y":3093,"x":1480,"groupId":201273},{"troopId":3,"tribeId":100002,"id":563,"y":3067,"x":1457,"groupId":206107},{"troopId":2,"tribeId":100002,"id":165,"y":3032,"x":1537,"groupId":200052},{"troopId":2,"tribeId":100002,"id":298,"y":3004,"x":1504,"groupId":206303},{"troopId":3,"tribeId":100134,"id":692,"y":4828,"x":1719,"groupId":206627},{"troopId":3,"tribeId":100002,"id":688,"y":3043,"x":1505,"groupId":201638},{"troopId":14,"tribeId":100002,"id":729,"y":3000,"x":1690,"groupId":200006},{"troopId":4,"tribeId":100002,"id":730,"y":3366,"x":1803,"groupId":206712},{"troopId":4,"tribeId":100213,"id":465,"y":3729,"x":411,"groupId":202219},{"troopId":4,"tribeId":100002,"id":75,"y":3098,"x":1841,"groupId":205970},{"troopId":2,"tribeId":100013,"id":161,"y":3076,"x":1946,"groupId":206373},{"troopId":2,"tribeId":100013,"id":358,"y":3051,"x":2000,"groupId":201473},{"troopId":3,"tribeId":100190,"id":881,"y":3070,"x":2193,"groupId":203938},{"troopId":2,"tribeId":100375,"id":548,"y":3057,"x":2573,"groupId":4000220},{"troopId":3,"tribeId":100375,"id":974,"y":3009,"x":2500,"groupId":203057},{"troopId":2,"tribeId":100375,"id":973,"y":3054,"x":2632,"groupId":203057},{"troopId":2,"tribeId":100304,"id":359,"y":3045,"x":2723,"groupId":204477},{"troopId":2,"tribeId":100249,"id":406,"y":3163,"x":854,"groupId":206256},{"troopId":2,"tribeId":100025,"id":108,"y":3731,"x":412,"groupId":4000004},{"troopId":4,"tribeId":100002,"id":564,"y":3131,"x":1489,"groupId":206107},{"troopId":5,"tribeId":100002,"id":566,"y":3165,"x":1506,"groupId":206107},{"troopId":6,"tribeId":100025,"id":400,"y":3366,"x":605,"groupId":204362},{"troopId":4,"tribeId":100002,"id":1149,"y":3196,"x":1957,"groupId":201543},{"troopId":3,"tribeId":100190,"id":514,"y":3129,"x":2249,"groupId":201789},{"troopId":2,"tribeId":100190,"id":202,"y":3142,"x":2420,"groupId":4000942},{"troopId":2,"tribeId":100375,"id":1378,"y":3122,"x":2711,"groupId":204274},{"troopId":3,"tribeId":100304,"id":355,"y":3131,"x":2723,"groupId":204477},{"troopId":5,"tribeId":100054,"id":171,"y":3280,"x":1293,"groupId":205957},{"troopId":4,"tribeId":100054,"id":345,"y":3234,"x":1293,"groupId":200865},{"troopId":2,"tribeId":100002,"id":516,"y":3220,"x":1701,"groupId":200011},{"troopId":2,"tribeId":100025,"id":90,"y":3660,"x":377,"groupId":4000200},{"troopId":2,"tribeId":100002,"id":1150,"y":3263,"x":1824,"groupId":201543},{"troopId":3,"tribeId":100002,"id":335,"y":3238,"x":1900,"groupId":4001093},{"troopId":3,"tribeId":100054,"id":428,"y":4643,"x":1686,"groupId":4000401},{"troopId":3,"tribeId":100025,"id":305,"y":3628,"x":361,"groupId":4000027},{"troopId":3,"tribeId":100190,"id":725,"y":3295,"x":2365,"groupId":202418},{"troopId":3,"tribeId":100190,"id":25,"y":3206,"x":2406,"groupId":4001141},{"troopId":2,"tribeId":0,"id":377,"y":3318,"x":489,"groupId":205021},{"troopId":5,"tribeId":100054,"id":542,"y":3330,"x":1238,"groupId":201249},{"troopId":2,"tribeId":100061,"id":1033,"y":3394,"x":1209,"groupId":201116},{"troopId":7,"tribeId":100054,"id":1031,"y":3387,"x":1366,"groupId":201322},{"troopId":7,"tribeId":100061,"id":281,"y":3325,"x":1535,"groupId":4000415},{"troopId":7,"tribeId":100061,"id":60,"y":3368,"x":1618,"groupId":4001447},{"troopId":2,"tribeId":1000020,"id":201,"y":3311,"x":1607,"groupId":206348},{"troopId":5,"tribeId":100002,"id":1148,"y":3387,"x":1859,"groupId":201543},{"troopId":2,"tribeId":100002,"id":992,"y":3394,"x":1841,"groupId":206031},{"troopId":4,"tribeId":100025,"id":77,"y":3691,"x":392,"groupId":4001204},{"troopId":2,"tribeId":100002,"id":1489,"y":3341,"x":1837,"groupId":200188},{"troopId":3,"tribeId":100002,"id":993,"y":3397,"x":1839,"groupId":206031},{"troopId":3,"tribeId":100280,"id":577,"y":5328,"x":1503,"groupId":205665},{"troopId":5,"tribeId":100002,"id":610,"y":3352,"x":1803,"groupId":4000617},{"troopId":4,"tribeId":100002,"id":994,"y":3393,"x":1955,"groupId":206031},{"troopId":2,"tribeId":100002,"id":751,"y":3312,"x":1903,"groupId":204425},{"troopId":2,"tribeId":100280,"id":578,"y":5328,"x":1503,"groupId":205665},{"troopId":2,"tribeId":100249,"id":381,"y":3460,"x":652,"groupId":205641},{"troopId":2,"tribeId":100249,"id":78,"y":3431,"x":638,"groupId":4001198},{"troopId":4,"tribeId":100025,"id":812,"y":3499,"x":671,"groupId":202298},{"troopId":3,"tribeId":100134,"id":333,"y":4351,"x":1691,"groupId":4000625},{"troopId":3,"tribeId":100061,"id":626,"y":3498,"x":1141,"groupId":206244},{"troopId":6,"tribeId":100054,"id":1030,"y":3419,"x":1179,"groupId":201322},{"troopId":2,"tribeId":100054,"id":569,"y":3494,"x":1207,"groupId":206159},{"troopId":11,"tribeId":100061,"id":625,"y":3448,"x":1250,"groupId":206244},{"troopId":4,"tribeId":100061,"id":308,"y":3479,"x":1799,"groupId":206334},{"troopId":3,"tribeId":100134,"id":771,"y":3461,"x":1929,"groupId":205677},{"troopId":3,"tribeId":100061,"id":46,"y":3406,"x":1923,"groupId":4001485},{"troopId":2,"tribeId":100190,"id":366,"y":3401,"x":2134,"groupId":206844},{"troopId":2,"tribeId":100190,"id":480,"y":3484,"x":2513,"groupId":4000139},{"troopId":2,"tribeId":100216,"id":142,"y":3443,"x":2792,"groupId":4000540},{"troopId":2,"tribeId":100061,"id":263,"y":3658,"x":1710,"groupId":205715},{"troopId":7,"tribeId":100213,"id":264,"y":3582,"x":361,"groupId":206696},{"troopId":4,"tribeId":100025,"id":871,"y":3553,"x":374,"groupId":206294},{"troopId":2,"tribeId":100025,"id":140,"y":3546,"x":378,"groupId":206399},{"troopId":2,"tribeId":100025,"id":224,"y":3562,"x":370,"groupId":4000632},{"troopId":2,"tribeId":100025,"id":38,"y":3504,"x":399,"groupId":4001109},{"troopId":9,"tribeId":100213,"id":268,"y":3582,"x":361,"groupId":206696},{"troopId":8,"tribeId":100213,"id":267,"y":3552,"x":376,"groupId":206696},{"troopId":3,"tribeId":100213,"id":269,"y":3582,"x":361,"groupId":206696},{"troopId":2,"tribeId":100002,"id":270,"y":3819,"x":1846,"groupId":201484},{"troopId":2,"tribeId":100025,"id":72,"y":3506,"x":398,"groupId":206521},{"troopId":6,"tribeId":100213,"id":266,"y":3553,"x":375,"groupId":206696},{"troopId":2,"tribeId":100025,"id":250,"y":3576,"x":363,"groupId":205973},{"troopId":3,"tribeId":100054,"id":570,"y":3537,"x":1363,"groupId":206159},{"troopId":2,"tribeId":100002,"id":436,"y":3555,"x":1756,"groupId":200179},{"troopId":2,"tribeId":100054,"id":30,"y":3524,"x":1821,"groupId":4001390},{"troopId":5,"tribeId":100002,"id":580,"y":3549,"x":1898,"groupId":4000244},{"troopId":2,"tribeId":100002,"id":581,"y":3552,"x":1901,"groupId":4000244},{"troopId":2,"tribeId":100134,"id":1165,"y":3589,"x":2033,"groupId":200883},{"troopId":4,"tribeId":100025,"id":227,"y":3628,"x":361,"groupId":203480},{"troopId":2,"tribeId":100025,"id":154,"y":3651,"x":372,"groupId":4000650},{"troopId":8,"tribeId":100054,"id":809,"y":3670,"x":1331,"groupId":205598},{"troopId":3,"tribeId":100025,"id":395,"y":3694,"x":394,"groupId":201855},{"troopId":2,"tribeId":100048,"id":69,"y":4723,"x":1261,"groupId":4000890},{"troopId":2,"tribeId":100025,"id":802,"y":3642,"x":368,"groupId":206402},{"troopId":3,"tribeId":100213,"id":303,"y":3604,"x":350,"groupId":4000201},{"troopId":2,"tribeId":100213,"id":302,"y":3604,"x":350,"groupId":4000201},{"troopId":5,"tribeId":100025,"id":1103,"y":3645,"x":369,"groupId":205191},{"troopId":5,"tribeId":100213,"id":468,"y":3640,"x":367,"groupId":202219},{"troopId":5,"tribeId":100025,"id":560,"y":3685,"x":389,"groupId":203260},{"troopId":2,"tribeId":100025,"id":398,"y":3678,"x":386,"groupId":204362},{"troopId":2,"tribeId":100025,"id":186,"y":3688,"x":391,"groupId":203155},{"troopId":5,"tribeId":100213,"id":707,"y":3607,"x":350,"groupId":205792},{"troopId":3,"tribeId":100025,"id":323,"y":3642,"x":368,"groupId":202060},{"troopId":2,"tribeId":100190,"id":328,"y":4635,"x":1743,"groupId":4000222},{"troopId":2,"tribeId":100213,"id":704,"y":3608,"x":351,"groupId":205792},{"troopId":13,"tribeId":100002,"id":461,"y":4252,"x":2360,"groupId":4000171},{"troopId":11,"tribeId":100213,"id":460,"y":3641,"x":367,"groupId":202219},{"troopId":4,"tribeId":100213,"id":706,"y":3608,"x":351,"groupId":205792},{"troopId":3,"tribeId":100213,"id":705,"y":3608,"x":351,"groupId":205792},{"troopId":2,"tribeId":100054,"id":811,"y":3955,"x":1473,"groupId":205598},{"troopId":5,"tribeId":100054,"id":1032,"y":3626,"x":1283,"groupId":201322},{"troopId":5,"tribeId":100025,"id":808,"y":3738,"x":416,"groupId":206402},{"troopId":2,"tribeId":100061,"id":47,"y":3640,"x":1757,"groupId":4001485},{"troopId":2,"tribeId":100061,"id":675,"y":3694,"x":1760,"groupId":200476},{"troopId":2,"tribeId":100061,"id":429,"y":3678,"x":1773,"groupId":201597},{"troopId":2,"tribeId":100304,"id":450,"y":3617,"x":2777,"groupId":206384},{"troopId":2,"tribeId":100304,"id":212,"y":3619,"x":2723,"groupId":206166},{"troopId":2,"tribeId":100304,"id":185,"y":3615,"x":2723,"groupId":4001314},{"troopId":9,"tribeId":100025,"id":1111,"y":3702,"x":398,"groupId":205191},{"troopId":14,"tribeId":100002,"id":471,"y":4289,"x":2260,"groupId":4000171},{"troopId":2,"tribeId":100025,"id":105,"y":3708,"x":401,"groupId":4000822},{"troopId":2,"tribeId":100025,"id":800,"y":3716,"x":405,"groupId":202298},{"troopId":2,"tribeId":100002,"id":467,"y":4002,"x":2328,"groupId":4000171},{"troopId":3,"tribeId":100025,"id":117,"y":3770,"x":432,"groupId":206335},{"troopId":2,"tribeId":100061,"id":57,"y":3773,"x":1569,"groupId":4001447},{"troopId":2,"tribeId":100061,"id":827,"y":3761,"x":1944,"groupId":201135},{"troopId":2,"tribeId":100190,"id":118,"y":3735,"x":2283,"groupId":4000987},{"troopId":2,"tribeId":100054,"id":1319,"y":3841,"x":1623,"groupId":201382},{"troopId":2,"tribeId":100134,"id":288,"y":3802,"x":2059,"groupId":4000511},{"troopId":2,"tribeId":100025,"id":153,"y":3982,"x":856,"groupId":203060},{"troopId":2,"tribeId":100249,"id":643,"y":3986,"x":1354,"groupId":201763},{"troopId":2,"tribeId":100025,"id":262,"y":3928,"x":1418,"groupId":203528},{"troopId":3,"tribeId":100375,"id":151,"y":3930,"x":2229,"groupId":4000196},{"troopId":2,"tribeId":100048,"id":92,"y":5436,"x":1598,"groupId":4001234},{"troopId":2,"tribeId":100061,"id":422,"y":3958,"x":2201,"groupId":201698},{"troopId":2,"tribeId":100167,"id":145,"y":4001,"x":758,"groupId":205615},{"troopId":8,"tribeId":100025,"id":1123,"y":4033,"x":1164,"groupId":205191},{"troopId":2,"tribeId":100249,"id":222,"y":4010,"x":1307,"groupId":4000863},{"troopId":2,"tribeId":100249,"id":334,"y":4004,"x":1309,"groupId":206826},{"troopId":2,"tribeId":100061,"id":829,"y":4076,"x":1599,"groupId":200541},{"troopId":3,"tribeId":100061,"id":828,"y":4008,"x":1978,"groupId":201135},{"troopId":3,"tribeId":100025,"id":1119,"y":4130,"x":1253,"groupId":205191},{"troopId":4,"tribeId":100025,"id":1120,"y":4148,"x":1279,"groupId":205191},{"troopId":7,"tribeId":100054,"id":810,"y":4188,"x":1590,"groupId":205598},{"troopId":2,"tribeId":100190,"id":61,"y":4130,"x":2293,"groupId":4001170},{"troopId":2,"tribeId":100167,"id":44,"y":4296,"x":1820,"groupId":4001434},{"troopId":4,"tribeId":100002,"id":472,"y":4250,"x":2308,"groupId":4000171},{"troopId":2,"tribeId":100002,"id":719,"y":4250,"x":2325,"groupId":204855},{"troopId":3,"tribeId":100002,"id":469,"y":4270,"x":2405,"groupId":4000171},{"troopId":2,"tribeId":100048,"id":76,"y":4388,"x":1429,"groupId":206364},{"troopId":3,"tribeId":100048,"id":585,"y":4350,"x":1448,"groupId":200080},{"troopId":7,"tribeId":100054,"id":432,"y":4325,"x":1686,"groupId":4000401},{"troopId":3,"tribeId":100190,"id":420,"y":4396,"x":1774,"groupId":202199},{"troopId":5,"tribeId":100190,"id":349,"y":4387,"x":2460,"groupId":4000808},{"troopId":3,"tribeId":100190,"id":347,"y":4449,"x":2460,"groupId":4000808},{"troopId":3,"tribeId":100025,"id":822,"y":4672,"x":962,"groupId":206165},{"troopId":5,"tribeId":100025,"id":820,"y":4655,"x":942,"groupId":206165},{"troopId":3,"tribeId":100025,"id":401,"y":4640,"x":1336,"groupId":204362},{"troopId":5,"tribeId":100054,"id":150,"y":4658,"x":1794,"groupId":203696},{"troopId":3,"tribeId":100054,"id":31,"y":4653,"x":1885,"groupId":4001390},{"troopId":7,"tribeId":100190,"id":351,"y":4648,"x":2390,"groupId":4000808},{"troopId":2,"tribeId":100048,"id":584,"y":4784,"x":1231,"groupId":200080},{"troopId":2,"tribeId":100054,"id":427,"y":4727,"x":1584,"groupId":4000401},{"troopId":8,"tribeId":100190,"id":352,"y":4762,"x":2310,"groupId":4000808},{"troopId":3,"tribeId":100134,"id":1000,"y":4846,"x":1728,"groupId":201724},{"troopId":3,"tribeId":100134,"id":1682,"y":4863,"x":1736,"groupId":200750},{"troopId":6,"tribeId":100134,"id":1685,"y":4819,"x":1714,"groupId":200750},{"troopId":4,"tribeId":100058,"id":894,"y":4946,"x":1875,"groupId":203507},{"troopId":6,"tribeId":100025,"id":1121,"y":5094,"x":1246,"groupId":205191},{"troopId":2,"tribeId":100280,"id":435,"y":5096,"x":1503,"groupId":203910},{"troopId":5,"tribeId":100058,"id":895,"y":5024,"x":1875,"groupId":203507},{"troopId":2,"tribeId":100054,"id":615,"y":5200,"x":2487,"groupId":206057},{"troopId":2,"tribeId":100280,"id":421,"y":5328,"x":1503,"groupId":204392},{"troopId":2,"tribeId":100280,"id":285,"y":5328,"x":1503,"groupId":4000286},{"troopId":2,"tribeId":100280,"id":73,"y":5328,"x":1503,"groupId":4000843},{"troopId":2,"tribeId":100280,"id":141,"y":5328,"x":1503,"groupId":4001091},{"troopId":2,"tribeId":100280,"id":16,"y":5328,"x":1503,"groupId":4001625},{"troopId":2,"tribeId":100280,"id":364,"y":5328,"x":1503,"groupId":205398},{"troopId":2,"tribeId":100280,"id":111,"y":5328,"x":1503,"groupId":4000217},{"troopId":5,"tribeId":100025,"id":385,"y":5463,"x":1654,"groupId":4000409},{"troopId":4,"tribeId":100025,"id":384,"y":5482,"x":1649,"groupId":4000409},{"troopId":3,"tribeId":100025,"id":383,"y":5521,"x":1642,"groupId":4000409},{"troopId":6,"tribeId":100025,"id":386,"y":5530,"x":1656,"groupId":4000409},{"troopId":7,"tribeId":100025,"id":387,"y":5727,"x":1654,"groupId":4000409}],"Strongholds":[{"name":"Lingones","level":2,"tribeId":1000020,"groupId":10000003,"time":"2013-04-12T03:00:01.738540Z","y":3327,"x":1875,"id":5036},{"name":"Yohan","level":2,"tribeId":100002,"groupId":10000003,"time":"2013-04-12T02:00:01.738540Z","y":1419,"x":2284,"id":5026},{"name":"Eira","level":2,"tribeId":100213,"groupId":10000003,"time":"2013-04-12T02:00:01.738540Z","y":2804,"x":324,"id":5028},{"name":"Ipslore","level":1,"tribeId":100013,"groupId":10000003,"time":"2013-04-12T02:00:01.738540Z","y":2882,"x":2106,"id":5010},{"name":"Duirmir","level":3,"tribeId":100134,"groupId":10000003,"time":"2013-04-12T02:00:01.738540Z","y":3720,"x":1644,"id":5050},{"name":"Ordovices","level":2,"tribeId":100134,"groupId":10000003,"time":"2013-04-12T01:00:01.738540Z","y":1148,"x":1884,"id":5034},{"name":"Irmpetiir","level":1,"tribeId":100134,"groupId":10000003,"time":"2013-04-11T23:00:01.738540Z","y":4276,"x":1916,"id":5003},{"name":"Elgenblot","level":3,"tribeId":100134,"groupId":10000003,"time":"2013-04-11T20:00:01.738540Z","y":4517,"x":1806,"id":5043},{"name":"Swiftbrand","level":13,"tribeId":0,"groupId":10000003,"time":"2013-04-11T17:00:01.738540Z","y":637,"x":1909,"id":5193},{"name":"Widefarer","level":13,"tribeId":100061,"groupId":10000003,"time":"2013-04-11T15:00:01.738540Z","y":3568,"x":1102,"id":5189},{"name":"Windslife","level":19,"tribeId":100061,"groupId":10000003,"time":"2013-04-11T13:00:01.738540Z","y":2122,"x":2271,"id":5237},{"name":"Beerfoot","level":5,"tribeId":100213,"groupId":10000003,"time":"2013-04-11T13:00:01.738540Z","y":2630,"x":588,"id":5080},{"name":"Lingones","level":2,"tribeId":100013,"groupId":10000003,"time":"2013-04-11T13:00:01.738540Z","y":3327,"x":1875,"id":5036},{"name":"Yohan","level":2,"tribeId":100205,"groupId":10000003,"time":"2013-04-11T12:00:01.738540Z","y":1419,"x":2284,"id":5026},{"name":"Celegon","level":7,"tribeId":100058,"groupId":10000003,"time":"2013-04-11T12:00:01.738540Z","y":5404,"x":1691,"id":5114},{"name":"Spitfire","level":1,"tribeId":100134,"groupId":10000003,"time":"2013-04-11T11:00:01.738540Z","y":1394,"x":926,"id":5013}]}