[
  {
    "tribeId": 100038,
    "color": "#c1f36c"
  },
  {
    "tribeId": 100328,
    "color": "#28babe"
  },
  {
    "tribeId": 100205,
    "color": "#593315"
  },
  {
    "tribeId": 100272,
    "color": "#53377a"
  },
  {
    "tribeId": 100167,
    "color": "#c10020"
  },
  {
    "tribeId": 100195,
    "color": "#befab8"
  },
  {
    "tribeId": 100025,
    "color": "#ff8e00"
  },
  {
    "tribeId": 100061,
    "color": "#a6bdd7"
  },
  {
    "tribeId": 1000024,
    "color": "#5fe73e"
  },
  {
    "tribeId": 100371,
    "color": "#76467f"
  },
  {
    "tribeId": 100048,
    "color": "#cea262"
  },
  {
    "tribeId": 100213,
    "color": "#f6768e"
  },
  {
    "tribeId": 1000063,
    "color": "#3767bc"
  },
  {
    "tribeId": 100190,
    "color": "#007d34"
  },
  {
    "tribeId": 100364,
    "color": "#105a78"
  },
  {
    "tribeId": 100293,
    "color": "#232c16"
  },
  {
    "tribeId": 100351,
    "color": "#f4151f"
  },
  {
    "tribeId": 100241,
    "color": "#6d3615"
  },
  {
    "tribeId": 100218,
    "color": "#d43ab9"
  },
  {
    "tribeId": 100249,
    "color": "#f4c800"
  },
  {
    "tribeId": 1000066,
    "color": "#b651ac"
  },
  {
    "tribeId": 100308,
    "color": "#6e593c"
  },
  {
    "tribeId": 100372,
    "color": "#072d50"
  },
  {
    "tribeId": 100245,
    "color": "#f71912"
  },
  {
    "tribeId": 100134,
    "color": "#f13a13"
  },
  {
    "tribeId": 100174,
    "color": "#6e7aeb"
  },
  {
    "tribeId": 1000029,
    "color": "#f13e21"
  },
  {
    "tribeId": 100002,
    "color": "#803e75"
  },
  {
    "tribeId": 100280,
    "color": "#b32851"
  },
  {
    "tribeId": 100327,
    "color": "#3bc410"
  },
  {
    "tribeId": 100233,
    "color": "#49f123"
  },
  {
    "tribeId": 100266,
    "color": "#c3ccdd"
  },
  {
    "tribeId": 100478,
    "color": "#4cb984"
  },
  {
    "tribeId": 100254,
    "color": "#a9e9c0"
  },
  {
    "tribeId": 100358,
    "color": "#fea796"
  },
  {
    "tribeId": 100054,
    "color": "#ff6800"
  },
  {
    "tribeId": 100279,
    "color": "#9108ec"
  },
  {
    "tribeId": 100429,
    "color": "#432f3a"
  },
  {
    "tribeId": 1000051,
    "color": "#6b1840"
  },
  {
    "tribeId": 1000076,
    "color": "#65869a"
  },
  {
    "tribeId": 100165,
    "color": "#337bf6"
  },
  {
    "tribeId": 100094,
    "color": "#f29975"
  },
  {
    "tribeId": 1000019,
    "color": "#a96c5e"
  },
  {
    "tribeId": 100153,
    "color": "#88a98b"
  },
  {
    "tribeId": 100138,
    "color": "#5dba72"
  },
  {
    "tribeId": 100187,
    "color": "#ca4e2f"
  },
  {
    "tribeId": 100180,
    "color": "#516ed1"
  },
  {
    "tribeId": 100432,
    "color": "#555f36"
  },
  {
    "tribeId": 1000031,
    "color": "#34f794"
  },
  {
    "tribeId": 100318,
    "color": "#d4ddd9"
  },
  {
    "tribeId": 100314,
    "color": "#e25d45"
  },
  {
    "tribeId": 100219,
    "color": "#43193d"
  },
  {
    "tribeId": 100136,
    "color": "#8db54f"
  },
  {
    "tribeId": 100306,
    "color": "#4a553a"
  },
  {
    "tribeId": 100476,
    "color": "#37095d"
  },
  {
    "tribeId": 100452,
    "color": "#60e474"
  },
  {
    "tribeId": 100442,
    "color": "#c69fc9"
  },
  {
    "tribeId": 100415,
    "color": "#101417"
  },
  {
    "tribeId": 100179,
    "color": "#c7dd1b"
  },
  {
    "tribeId": 100192,
    "color": "#c0bea0"
  },
  {
    "tribeId": 100224,
    "color": "#dfd38e"
  },
  {
    "tribeId": 100394,
    "color": "#84a54b"
  },
  {
    "tribeId": 1000047,
    "color": "#451aa0"
  },
  {
    "tribeId": 100216,
    "color": "#93aa00"
  },
  {
    "tribeId": 1000023,
    "color": "#343d97"
  },
  {
    "tribeId": 100325,
    "color": "#de0619"
  },
  {
    "tribeId": 100399,
    "color": "#961d56"
  },
  {
    "tribeId": 100256,
    "color": "#d7d212"
  },
  {
    "tribeId": 100013,
    "color": "#ffb300"
  },
  {
    "tribeId": 100386,
    "color": "#200e3d"
  },
  {
    "tribeId": 100375,
    "color": "#00538a"
  },
  {
    "tribeId": 1000053,
    "color": "#10d148"
  },
  {
    "tribeId": 100210,
    "color": "#2e7b3b"
  },
  {
    "tribeId": 100244,
    "color": "#22ccf5"
  },
  {
    "tribeId": 100008,
    "color": "#ae6a81"
  },
  {
    "tribeId": 100261,
    "color": "#abb263"
  },
  {
    "tribeId": 100477,
    "color": "#111aca"
  },
  {
    "tribeId": 100292,
    "color": "#d29161"
  },
  {
    "tribeId": 100191,
    "color": "#31300e"
  },
  {
    "tribeId": 100122,
    "color": "#fd30c0"
  },
  {
    "tribeId": 100235,
    "color": "#c4e7eb"
  },
  {
    "tribeId": 100162,
    "color": "#8dbfc4"
  },
  {
    "tribeId": 100234,
    "color": "#5174d2"
  },
  {
    "tribeId": 100252,
    "color": "#03179e"
  },
  {
    "tribeId": 100264,
    "color": "#651270"
  },
  {
    "tribeId": 100298,
    "color": "#a0309a"
  },
  {
    "tribeId": 100288,
    "color": "#97ea69"
  },
  {
    "tribeId": 100246,
    "color": "#f1c5b7"
  },
  {
    "tribeId": 100076,
    "color": "#474c7b"
  },
  {
    "tribeId": 100081,
    "color": "#dadda0"
  },
  {
    "tribeId": 100156,
    "color": "#39304a"
  },
  {
    "tribeId": 100437,
    "color": "#7a5ce3"
  },
  {
    "tribeId": 100355,
    "color": "#0a20aa"
  },
  {
    "tribeId": 100290,
    "color": "#bb5a3e"
  },
  {
    "tribeId": 100380,
    "color": "#8f0e03"
  },
  {
    "tribeId": 100354,
    "color": "#2b6d7f"
  },
  {
    "tribeId": 100104,
    "color": "#f08f00"
  },
  {
    "tribeId": 100253,
    "color": "#736545"
  },
  {
    "tribeId": 100250,
    "color": "#56d121"
  },
  {
    "tribeId": 1000065,
    "color": "#334672"
  },
  {
    "tribeId": 100178,
    "color": "#497595"
  },
  {
    "tribeId": 100058,
    "color": "#ff7a5c"
  },
  {
    "tribeId": 100177,
    "color": "#32c8e6"
  },
  {
    "tribeId": 100356,
    "color": "#53eab4"
  },
  {
    "tribeId": 100140,
    "color": "#8b9610"
  },
  {
    "tribeId": 100077,
    "color": "#efdb90"
  },
  {
    "tribeId": 1000025,
    "color": "#2a62b7"
  },
  {
    "tribeId": 1000059,
    "color": "#b41cde"
  },
  {
    "tribeId": 100160,
    "color": "#fae94e"
  },
  {
    "tribeId": 100171,
    "color": "#a0c5c9"
  },
  {
    "tribeId": 100036,
    "color": "#052389"
  },
  {
    "tribeId": 100366,
    "color": "#c2d5d9"
  },
  {
    "tribeId": 100295,
    "color": "#3771e3"
  },
  {
    "tribeId": 100275,
    "color": "#a85d45"
  },
  {
    "tribeId": 100400,
    "color": "#1bd681"
  },
  {
    "tribeId": 100222,
    "color": "#c964f8"
  },
  {
    "tribeId": 100066,
    "color": "#ee8289"
  },
  {
    "tribeId": 100024,
    "color": "#b32c6f"
  },
  {
    "tribeId": 100350,
    "color": "#697e2a"
  },
  {
    "tribeId": 1000041,
    "color": "#934d8a"
  },
  {
    "tribeId": 100278,
    "color": "#479002"
  },
  {
    "tribeId": 100406,
    "color": "#1c4ec6"
  },
  {
    "tribeId": 100062,
    "color": "#2ac8bf"
  },
  {
    "tribeId": 1000075,
    "color": "#36b869"
  },
  {
    "tribeId": 1000054,
    "color": "#ab8104"
  },
  {
    "tribeId": 100349,
    "color": "#719844"
  },
  {
    "tribeId": 100363,
    "color": "#5c3185"
  },
  {
    "tribeId": 100123,
    "color": "#7f180d"
  },
  {
    "tribeId": 100073,
    "color": "#54b042"
  },
  {
    "tribeId": 100240,
    "color": "#4050f6"
  },
  {
    "tribeId": 100142,
    "color": "#1a5957"
  },
  {
    "tribeId": 100304,
    "color": "#817066"
  },
  {
    "tribeId": 100347,
    "color": "#aea223"
  },
  {
    "tribeId": 100017,
    "color": "#5960cb"
  },
  {
    "tribeId": 100112,
    "color": "#43fe88"
  },
  {
    "tribeId": 1000014,
    "color": "#ba9e9b"
  },
  {
    "tribeId": 100259,
    "color": "#39b8c9"
  },
  {
    "tribeId": 100427,
    "color": "#1f08a9"
  },
  {
    "tribeId": 100135,
    "color": "#6bf6e5"
  },
  {
    "tribeId": 100125,
    "color": "#e5371c"
  },
  {
    "tribeId": 100060,
    "color": "#05f1de"
  },
  {
    "tribeId": 100316,
    "color": "#bedafc"
  },
  {
    "tribeId": 100168,
    "color": "#cf106f"
  },
  {
    "tribeId": 100087,
    "color": "#678616"
  },
  {
    "tribeId": 100004,
    "color": "#465220"
  },
  {
    "tribeId": 100031,
    "color": "#372e98"
  },
  {
    "tribeId": 100258,
    "color": "#baa191"
  },
  {
    "tribeId": 100346,
    "color": "#e81bf7"
  },
  {
    "tribeId": 100396,
    "color": "#782148"
  },
  {
    "tribeId": 100342,
    "color": "#4dae61"
  },
  {
    "tribeId": 100132,
    "color": "#71c86a"
  },
  {
    "tribeId": 100211,
    "color": "#07536d"
  },
  {
    "tribeId": 100052,
    "color": "#eb8323"
  },
  {
    "tribeId": 100487,
    "color": "#8ae98e"
  },
  {
    "tribeId": 100018,
    "color": "#2bd031"
  },
  {
    "tribeId": 100080,
    "color": "#b3d8b5"
  },
  {
    "tribeId": 100044,
    "color": "#8833c8"
  },
  {
    "tribeId": 100370,
    "color": "#4c2a95"
  },
  {
    "tribeId": 100383,
    "color": "#8a1bd6"
  },
  {
    "tribeId": 100281,
    "color": "#e646b9"
  },
  {
    "tribeId": 100078,
    "color": "#b48261"
  },
  {
    "tribeId": 100009,
    "color": "#0ef5bc"
  },
  {
    "tribeId": 1000020,
    "color": "#aa3efd"
  },
  {
    "tribeId": 100046,
    "color": "#b24ba9"
  },
  {
    "tribeId": 100286,
    "color": "#752fb6"
  },
  {
    "tribeId": 100221,
    "color": "#03bd4a"
  },
  {
    "tribeId": 100200,
    "color": "#c5c448"
  },
  {
    "tribeId": 100384,
    "color": "#92c37a"
  },
  {
    "tribeId": 1000056,
    "color": "#97259e"
  },
  {
    "tribeId": 100032,
    "color": "#d47c37"
  },
  {
    "tribeId": 100248,
    "color": "#96053d"
  },
  {
    "tribeId": 100227,
    "color": "#69d567"
  },
  {
    "tribeId": 100289,
    "color": "#2c1dd9"
  },
  {
    "tribeId": 100373,
    "color": "#740999"
  },
  {
    "tribeId": 100014,
    "color": "#b6d5e7"
  },
  {
    "tribeId": 100064,
    "color": "#1fd5f9"
  },
  {
    "tribeId": 100409,
    "color": "#dd875d"
  },
  {
    "tribeId": 1000058,
    "color": "#8b2080"
  },
  {
    "tribeId": 100193,
    "color": "#7022bd"
  },
  {
    "tribeId": 100063,
    "color": "#e575d0"
  },
  {
    "tribeId": 100348,
    "color": "#1ed4c1"
  },
  {
    "tribeId": 100368,
    "color": "#c61b45"
  },
  {
    "tribeId": 100117,
    "color": "#6b0c59"
  },
  {
    "tribeId": 100095,
    "color": "#4ed59f"
  },
  {
    "tribeId": 100128,
    "color": "#6f51ba"
  },
  {
    "tribeId": 100184,
    "color": "#aedaed"
  },
  {
    "tribeId": 100488,
    "color": "#92774e"
  },
  {
    "tribeId": 100340,
    "color": "#a3f5f4"
  },
  {
    "tribeId": 1000036,
    "color": "#d80ae3"
  },
  {
    "tribeId": 100106,
    "color": "#bbf7b3"
  },
  {
    "tribeId": 100451,
    "color": "#a846a6"
  },
  {
    "tribeId": 100172,
    "color": "#095633"
  },
  {
    "tribeId": 1000073,
    "color": "#d6efb9"
  },
  {
    "tribeId": 100379,
    "color": "#a1b2c9"
  },
  {
    "tribeId": 100239,
    "color": "#a08eb0"
  },
  {
    "tribeId": 100291,
    "color": "#bd1cce"
  },
  {
    "tribeId": 100035,
    "color": "#c5c146"
  },
  {
    "tribeId": 1000069,
    "color": "#cf52fc"
  },
  {
    "tribeId": 100455,
    "color": "#8179dd"
  },
  {
    "tribeId": 100139,
    "color": "#ccec10"
  },
  {
    "tribeId": 100336,
    "color": "#61ae14"
  },
  {
    "tribeId": 100411,
    "color": "#a5a58f"
  },
  {
    "tribeId": 100242,
    "color": "#f865f9"
  },
  {
    "tribeId": 100148,
    "color": "#87d6ea"
  },
  {
    "tribeId": 100145,
    "color": "#33f0c4"
  },
  {
    "tribeId": 100466,
    "color": "#840366"
  },
  {
    "tribeId": 100334,
    "color": "#431bed"
  },
  {
    "tribeId": 100322,
    "color": "#14f535"
  },
  {
    "tribeId": 100057,
    "color": "#6cd7f2"
  },
  {
    "tribeId": 100051,
    "color": "#a887dc"
  },
  {
    "tribeId": 100482,
    "color": "#540a02"
  },
  {
    "tribeId": 100268,
    "color": "#a84003"
  },
  {
    "tribeId": 1000078,
    "color": "#b5fae8"
  },
  {
    "tribeId": 100204,
    "color": "#21c4b5"
  },
  {
    "tribeId": 100317,
    "color": "#d33dea"
  },
  {
    "tribeId": 100407,
    "color": "#5b9c61"
  },
  {
    "tribeId": 100282,
    "color": "#38fb75"
  },
  {
    "tribeId": 100486,
    "color": "#7689d0"
  },
  {
    "tribeId": 100301,
    "color": "#224cb8"
  },
  {
    "tribeId": 100362,
    "color": "#dd38cc"
  },
  {
    "tribeId": 100311,
    "color": "#9c4fdd"
  },
  {
    "tribeId": 100126,
    "color": "#1d32cc"
  },
  {
    "tribeId": 100357,
    "color": "#e789af"
  },
  {
    "tribeId": 1000060,
    "color": "#c0ce08"
  },
  {
    "tribeId": 100161,
    "color": "#7d2256"
  },
  {
    "tribeId": 100294,
    "color": "#3740b8"
  },
  {
    "tribeId": 100446,
    "color": "#49113b"
  },
  {
    "tribeId": 100393,
    "color": "#906f8a"
  },
  {
    "tribeId": 100209,
    "color": "#66dc80"
  },
  {
    "tribeId": 1000062,
    "color": "#3185f3"
  },
  {
    "tribeId": 1000055,
    "color": "#4ad6c1"
  },
  {
    "tribeId": 100223,
    "color": "#1c8474"
  },
  {
    "tribeId": 1000026,
    "color": "#d7b50b"
  },
  {
    "tribeId": 100214,
    "color": "#1e7213"
  },
  {
    "tribeId": 100196,
    "color": "#b1762d"
  },
  {
    "tribeId": 100232,
    "color": "#6cf867"
  },
  {
    "tribeId": 100181,
    "color": "#79ea0c"
  },
  {
    "tribeId": 100450,
    "color": "#009327"
  },
  {
    "tribeId": 100439,
    "color": "#900bde"
  },
  {
    "tribeId": 100391,
    "color": "#53b654"
  },
  {
    "tribeId": 100436,
    "color": "#4cb603"
  },
  {
    "tribeId": 100320,
    "color": "#bb76f6"
  },
  {
    "tribeId": 100472,
    "color": "#45619c"
  },
  {
    "tribeId": 100475,
    "color": "#e15e89"
  }
]