[
  {
    "tribeId": 100038,
    "color": "#a738c6"
  },
  {
    "tribeId": 100328,
    "color": "#6b7ccb"
  },
  {
    "tribeId": 100205,
    "color": "#593315"
  },
  {
    "tribeId": 100249,
    "color": "#f4c800"
  },
  {
    "tribeId": 1000076,
    "color": "#cd9034"
  },
  {
    "tribeId": 100167,
    "color": "#c10020"
  },
  {
    "tribeId": 100195,
    "color": "#ffb300"
  },
  {
    "tribeId": 100025,
    "color": "#ff8e00"
  },
  {
    "tribeId": 100061,
    "color": "#a6bdd7"
  },
  {
    "tribeId": 1000024,
    "color": "#2fa0c9"
  },
  {
    "tribeId": 100371,
    "color": "#0e2ce0"
  },
  {
    "tribeId": 100375,
    "color": "#00538a"
  },
  {
    "tribeId": 100048,
    "color": "#cea262"
  },
  {
    "tribeId": 100213,
    "color": "#f6768e"
  },
  {
    "tribeId": 1000063,
    "color": "#5c7124"
  },
  {
    "tribeId": 100190,
    "color": "#007d34"
  },
  {
    "tribeId": 100364,
    "color": "#28f6d1"
  },
  {
    "tribeId": 100293,
    "color": "#232c16"
  },
  {
    "tribeId": 100351,
    "color": "#f71ed6"
  },
  {
    "tribeId": 100241,
    "color": "#211e67"
  },
  {
    "tribeId": 1000066,
    "color": "#efa4f3"
  },
  {
    "tribeId": 100272,
    "color": "#08cde1"
  },
  {
    "tribeId": 100308,
    "color": "#98782c"
  },
  {
    "tribeId": 100372,
    "color": "#491823"
  },
  {
    "tribeId": 100245,
    "color": "#f0224f"
  },
  {
    "tribeId": 100174,
    "color": "#e21ba6"
  },
  {
    "tribeId": 1000029,
    "color": "#ae0251"
  },
  {
    "tribeId": 100002,
    "color": "#803e75"
  },
  {
    "tribeId": 100280,
    "color": "#b32851"
  },
  {
    "tribeId": 100327,
    "color": "#d4c3d4"
  },
  {
    "tribeId": 100233,
    "color": "#dcc4a5"
  },
  {
    "tribeId": 100266,
    "color": "#a8af19"
  },
  {
    "tribeId": 100478,
    "color": "#ee495d"
  },
  {
    "tribeId": 100254,
    "color": "#63ddea"
  },
  {
    "tribeId": 100358,
    "color": "#4026d2"
  },
  {
    "tribeId": 100054,
    "color": "#ff6800"
  },
  {
    "tribeId": 100279,
    "color": "#e675b2"
  },
  {
    "tribeId": 100134,
    "color": "#f13a13"
  },
  {
    "tribeId": 100429,
    "color": "#b31258"
  },
  {
    "tribeId": 1000051,
    "color": "#0037d3"
  },
  {
    "tribeId": 100165,
    "color": "#811503"
  },
  {
    "tribeId": 100094,
    "color": "#2f721c"
  },
  {
    "tribeId": 1000019,
    "color": "#161be0"
  },
  {
    "tribeId": 100218,
    "color": "#1e2b08"
  },
  {
    "tribeId": 100138,
    "color": "#3ceec8"
  },
  {
    "tribeId": 100187,
    "color": "#135ace"
  },
  {
    "tribeId": 100180,
    "color": "#c58c44"
  },
  {
    "tribeId": 100432,
    "color": "#64a2f3"
  },
  {
    "tribeId": 1000031,
    "color": "#d3c68c"
  },
  {
    "tribeId": 100318,
    "color": "#9e20b0"
  },
  {
    "tribeId": 100314,
    "color": "#7cdb8d"
  },
  {
    "tribeId": 100219,
    "color": "#d02699"
  },
  {
    "tribeId": 100136,
    "color": "#15bed6"
  },
  {
    "tribeId": 100306,
    "color": "#414dc2"
  },
  {
    "tribeId": 100476,
    "color": "#0a21fa"
  },
  {
    "tribeId": 100452,
    "color": "#c9aa85"
  },
  {
    "tribeId": 100442,
    "color": "#e89fb7"
  },
  {
    "tribeId": 100415,
    "color": "#893aa9"
  },
  {
    "tribeId": 100179,
    "color": "#8f1d71"
  },
  {
    "tribeId": 100192,
    "color": "#0f5baa"
  },
  {
    "tribeId": 100224,
    "color": "#8e76f9"
  },
  {
    "tribeId": 100394,
    "color": "#2fa14e"
  },
  {
    "tribeId": 1000047,
    "color": "#7a6ac8"
  },
  {
    "tribeId": 100216,
    "color": "#93aa00"
  },
  {
    "tribeId": 1000023,
    "color": "#2efd9a"
  },
  {
    "tribeId": 100325,
    "color": "#f6843f"
  },
  {
    "tribeId": 100399,
    "color": "#805980"
  },
  {
    "tribeId": 100256,
    "color": "#f8091c"
  },
  {
    "tribeId": 100013,
    "color": "#53377a"
  },
  {
    "tribeId": 100386,
    "color": "#07b580"
  },
  {
    "tribeId": 1000053,
    "color": "#f7f2a0"
  },
  {
    "tribeId": 100210,
    "color": "#e34108"
  },
  {
    "tribeId": 100153,
    "color": "#280562"
  },
  {
    "tribeId": 100244,
    "color": "#2cb1d5"
  },
  {
    "tribeId": 100008,
    "color": "#c8d97f"
  },
  {
    "tribeId": 100261,
    "color": "#ab4f3f"
  },
  {
    "tribeId": 100477,
    "color": "#bbb9a1"
  },
  {
    "tribeId": 100292,
    "color": "#1c91b5"
  },
  {
    "tribeId": 100191,
    "color": "#690ec2"
  },
  {
    "tribeId": 100122,
    "color": "#ef1651"
  },
  {
    "tribeId": 100235,
    "color": "#8d87c0"
  },
  {
    "tribeId": 100162,
    "color": "#7836ae"
  },
  {
    "tribeId": 100234,
    "color": "#ac9529"
  },
  {
    "tribeId": 100252,
    "color": "#bf06f7"
  },
  {
    "tribeId": 100264,
    "color": "#37cad1"
  },
  {
    "tribeId": 100298,
    "color": "#69b77f"
  },
  {
    "tribeId": 100288,
    "color": "#014cb9"
  },
  {
    "tribeId": 100246,
    "color": "#dc4afa"
  },
  {
    "tribeId": 100076,
    "color": "#dddb60"
  },
  {
    "tribeId": 100081,
    "color": "#ea7932"
  },
  {
    "tribeId": 100156,
    "color": "#4537ee"
  },
  {
    "tribeId": 100437,
    "color": "#119d2a"
  },
  {
    "tribeId": 100355,
    "color": "#144fa2"
  },
  {
    "tribeId": 100290,
    "color": "#d0fdb9"
  },
  {
    "tribeId": 100380,
    "color": "#16fbb2"
  },
  {
    "tribeId": 100104,
    "color": "#a9e4c6"
  },
  {
    "tribeId": 100253,
    "color": "#e2fe55"
  },
  {
    "tribeId": 100250,
    "color": "#43edc8"
  },
  {
    "tribeId": 1000065,
    "color": "#97b03c"
  },
  {
    "tribeId": 100178,
    "color": "#c49a5a"
  },
  {
    "tribeId": 100058,
    "color": "#ff7a5c"
  },
  {
    "tribeId": 100177,
    "color": "#4ec11b"
  },
  {
    "tribeId": 100356,
    "color": "#f57acd"
  },
  {
    "tribeId": 100140,
    "color": "#08262c"
  },
  {
    "tribeId": 100077,
    "color": "#a75468"
  },
  {
    "tribeId": 1000025,
    "color": "#db304e"
  },
  {
    "tribeId": 1000059,
    "color": "#00c54d"
  },
  {
    "tribeId": 100160,
    "color": "#4734f5"
  },
  {
    "tribeId": 100171,
    "color": "#98077a"
  },
  {
    "tribeId": 100036,
    "color": "#db0148"
  },
  {
    "tribeId": 100366,
    "color": "#2679ec"
  },
  {
    "tribeId": 100295,
    "color": "#ec4eb3"
  },
  {
    "tribeId": 100275,
    "color": "#47823c"
  },
  {
    "tribeId": 100400,
    "color": "#9d1f81"
  },
  {
    "tribeId": 100222,
    "color": "#e4a0bd"
  },
  {
    "tribeId": 100066,
    "color": "#9a3ba9"
  },
  {
    "tribeId": 100024,
    "color": "#ec66bd"
  },
  {
    "tribeId": 100350,
    "color": "#7a97e9"
  },
  {
    "tribeId": 1000041,
    "color": "#ee7d65"
  },
  {
    "tribeId": 100278,
    "color": "#63b4b9"
  },
  {
    "tribeId": 100406,
    "color": "#a01978"
  },
  {
    "tribeId": 100062,
    "color": "#84e0ab"
  },
  {
    "tribeId": 1000075,
    "color": "#3eb906"
  },
  {
    "tribeId": 1000054,
    "color": "#b393ad"
  },
  {
    "tribeId": 100349,
    "color": "#1161a5"
  },
  {
    "tribeId": 100363,
    "color": "#cb6292"
  },
  {
    "tribeId": 100123,
    "color": "#7f180d"
  },
  {
    "tribeId": 100073,
    "color": "#37fdcb"
  },
  {
    "tribeId": 100240,
    "color": "#cfee99"
  },
  {
    "tribeId": 100142,
    "color": "#8aabe0"
  },
  {
    "tribeId": 100304,
    "color": "#817066"
  },
  {
    "tribeId": 100347,
    "color": "#02fdd0"
  },
  {
    "tribeId": 100017,
    "color": "#4ee3cc"
  },
  {
    "tribeId": 100112,
    "color": "#81fb06"
  },
  {
    "tribeId": 1000014,
    "color": "#0860be"
  },
  {
    "tribeId": 100259,
    "color": "#115b80"
  },
  {
    "tribeId": 100427,
    "color": "#a338d1"
  },
  {
    "tribeId": 100135,
    "color": "#106835"
  },
  {
    "tribeId": 100125,
    "color": "#44221a"
  },
  {
    "tribeId": 100060,
    "color": "#d22bb5"
  },
  {
    "tribeId": 100316,
    "color": "#edd02a"
  },
  {
    "tribeId": 100168,
    "color": "#ddf935"
  },
  {
    "tribeId": 100087,
    "color": "#ca3bbb"
  },
  {
    "tribeId": 100004,
    "color": "#3465af"
  },
  {
    "tribeId": 100031,
    "color": "#df8f64"
  },
  {
    "tribeId": 100354,
    "color": "#9fc202"
  },
  {
    "tribeId": 100258,
    "color": "#d225a2"
  },
  {
    "tribeId": 100346,
    "color": "#4a2bb5"
  },
  {
    "tribeId": 100396,
    "color": "#c67a42"
  },
  {
    "tribeId": 100342,
    "color": "#abbdda"
  },
  {
    "tribeId": 100132,
    "color": "#b57ab7"
  },
  {
    "tribeId": 100211,
    "color": "#17932b"
  },
  {
    "tribeId": 100052,
    "color": "#da2966"
  },
  {
    "tribeId": 100487,
    "color": "#89461f"
  },
  {
    "tribeId": 100018,
    "color": "#c46fd2"
  },
  {
    "tribeId": 100080,
    "color": "#222fd8"
  },
  {
    "tribeId": 100044,
    "color": "#cfa35f"
  },
  {
    "tribeId": 100370,
    "color": "#18fe05"
  },
  {
    "tribeId": 100383,
    "color": "#13a2a5"
  },
  {
    "tribeId": 100281,
    "color": "#73167e"
  },
  {
    "tribeId": 100078,
    "color": "#f11e7d"
  },
  {
    "tribeId": 100009,
    "color": "#df7de9"
  },
  {
    "tribeId": 1000020,
    "color": "#f7c8fa"
  },
  {
    "tribeId": 100046,
    "color": "#39c398"
  },
  {
    "tribeId": 100286,
    "color": "#9b49de"
  },
  {
    "tribeId": 100221,
    "color": "#8384bb"
  },
  {
    "tribeId": 100200,
    "color": "#e2a44a"
  },
  {
    "tribeId": 100384,
    "color": "#69da19"
  },
  {
    "tribeId": 1000056,
    "color": "#7b9d7b"
  },
  {
    "tribeId": 100032,
    "color": "#b104f0"
  },
  {
    "tribeId": 100248,
    "color": "#856713"
  },
  {
    "tribeId": 100227,
    "color": "#e69628"
  },
  {
    "tribeId": 100289,
    "color": "#a0e4f0"
  },
  {
    "tribeId": 100373,
    "color": "#e72966"
  },
  {
    "tribeId": 100014,
    "color": "#dc96de"
  },
  {
    "tribeId": 100064,
    "color": "#c57cb4"
  },
  {
    "tribeId": 100409,
    "color": "#268e1d"
  },
  {
    "tribeId": 1000058,
    "color": "#e89071"
  },
  {
    "tribeId": 100193,
    "color": "#348842"
  },
  {
    "tribeId": 100063,
    "color": "#6363de"
  },
  {
    "tribeId": 100348,
    "color": "#6e46c3"
  },
  {
    "tribeId": 100368,
    "color": "#0ab35c"
  },
  {
    "tribeId": 100117,
    "color": "#85b4b2"
  },
  {
    "tribeId": 100095,
    "color": "#b5e19f"
  },
  {
    "tribeId": 100128,
    "color": "#c9fa7a"
  },
  {
    "tribeId": 100184,
    "color": "#e28b44"
  },
  {
    "tribeId": 100488,
    "color": "#3ab521"
  },
  {
    "tribeId": 100340,
    "color": "#c58a74"
  },
  {
    "tribeId": 1000036,
    "color": "#d29bd5"
  },
  {
    "tribeId": 100106,
    "color": "#a0b10d"
  },
  {
    "tribeId": 100451,
    "color": "#e43d80"
  },
  {
    "tribeId": 100172,
    "color": "#1179e2"
  },
  {
    "tribeId": 1000073,
    "color": "#a1d2e1"
  },
  {
    "tribeId": 100239,
    "color": "#8240c6"
  },
  {
    "tribeId": 100291,
    "color": "#0270ac"
  },
  {
    "tribeId": 100035,
    "color": "#7c1f95"
  },
  {
    "tribeId": 1000069,
    "color": "#f551fb"
  },
  {
    "tribeId": 100455,
    "color": "#fd29ad"
  },
  {
    "tribeId": 100139,
    "color": "#bda7ba"
  },
  {
    "tribeId": 100336,
    "color": "#4f3617"
  },
  {
    "tribeId": 100411,
    "color": "#85e303"
  },
  {
    "tribeId": 100242,
    "color": "#a4d0a3"
  },
  {
    "tribeId": 100148,
    "color": "#1fb880"
  },
  {
    "tribeId": 100145,
    "color": "#9740b8"
  },
  {
    "tribeId": 100466,
    "color": "#61b674"
  },
  {
    "tribeId": 100334,
    "color": "#59c31a"
  },
  {
    "tribeId": 100322,
    "color": "#c7557c"
  },
  {
    "tribeId": 100057,
    "color": "#40aa5f"
  },
  {
    "tribeId": 100051,
    "color": "#11e614"
  },
  {
    "tribeId": 100482,
    "color": "#d153d0"
  },
  {
    "tribeId": 100268,
    "color": "#27529b"
  },
  {
    "tribeId": 1000078,
    "color": "#c9fb5b"
  },
  {
    "tribeId": 100204,
    "color": "#c35c9e"
  },
  {
    "tribeId": 100317,
    "color": "#085d66"
  },
  {
    "tribeId": 100407,
    "color": "#145d10"
  },
  {
    "tribeId": 100282,
    "color": "#439b71"
  },
  {
    "tribeId": 100486,
    "color": "#3863e3"
  },
  {
    "tribeId": 100301,
    "color": "#a087e0"
  },
  {
    "tribeId": 100379,
    "color": "#9a4538"
  },
  {
    "tribeId": 1000084,
    "color": "#a293e9"
  },
  {
    "tribeId": 100362,
    "color": "#8f4c64"
  },
  {
    "tribeId": 100311,
    "color": "#af6fed"
  },
  {
    "tribeId": 100126,
    "color": "#1c96ba"
  },
  {
    "tribeId": 100357,
    "color": "#199466"
  },
  {
    "tribeId": 1000060,
    "color": "#7abff7"
  },
  {
    "tribeId": 100161,
    "color": "#162c4c"
  },
  {
    "tribeId": 100294,
    "color": "#4ecc4a"
  },
  {
    "tribeId": 100446,
    "color": "#a199ee"
  },
  {
    "tribeId": 100393,
    "color": "#ec86ca"
  },
  {
    "tribeId": 100209,
    "color": "#ba2fb6"
  },
  {
    "tribeId": 1000062,
    "color": "#2221c8"
  },
  {
    "tribeId": 1000055,
    "color": "#b47710"
  },
  {
    "tribeId": 100223,
    "color": "#0163ed"
  },
  {
    "tribeId": 1000026,
    "color": "#222704"
  },
  {
    "tribeId": 100214,
    "color": "#b61fcd"
  },
  {
    "tribeId": 100196,
    "color": "#7c26c7"
  },
  {
    "tribeId": 100232,
    "color": "#e78418"
  },
  {
    "tribeId": 100181,
    "color": "#eb53c6"
  },
  {
    "tribeId": 100439,
    "color": "#9eecb2"
  },
  {
    "tribeId": 100391,
    "color": "#75c2e8"
  },
  {
    "tribeId": 100436,
    "color": "#226067"
  },
  {
    "tribeId": 100320,
    "color": "#04f573"
  },
  {
    "tribeId": 100472,
    "color": "#9dc447"
  },
  {
    "tribeId": 100475,
    "color": "#e614c7"
  }
]