[
  {
    "tribeId": 100038,
    "color": "#da8b8b"
  },
  {
    "tribeId": 100328,
    "color": "#fefe3d"
  },
  {
    "tribeId": 100205,
    "color": "#593315"
  },
  {
    "tribeId": 100249,
    "color": "#f4c800"
  },
  {
    "tribeId": 1000076,
    "color": "#a1d57f"
  },
  {
    "tribeId": 100167,
    "color": "#c10020"
  },
  {
    "tribeId": 100195,
    "color": "#ffb300"
  },
  {
    "tribeId": 100025,
    "color": "#ff8e00"
  },
  {
    "tribeId": 100061,
    "color": "#a6bdd7"
  },
  {
    "tribeId": 1000024,
    "color": "#c838ee"
  },
  {
    "tribeId": 100371,
    "color": "#543187"
  },
  {
    "tribeId": 100375,
    "color": "#00538a"
  },
  {
    "tribeId": 100048,
    "color": "#cea262"
  },
  {
    "tribeId": 1000063,
    "color": "#f867bb"
  },
  {
    "tribeId": 100190,
    "color": "#007d34"
  },
  {
    "tribeId": 100364,
    "color": "#a395cd"
  },
  {
    "tribeId": 100293,
    "color": "#232c16"
  },
  {
    "tribeId": 100351,
    "color": "#c222b2"
  },
  {
    "tribeId": 100241,
    "color": "#7a0e42"
  },
  {
    "tribeId": 100218,
    "color": "#21f912"
  },
  {
    "tribeId": 1000066,
    "color": "#92ac9d"
  },
  {
    "tribeId": 100272,
    "color": "#53377a"
  },
  {
    "tribeId": 100308,
    "color": "#5057da"
  },
  {
    "tribeId": 100372,
    "color": "#f8a484"
  },
  {
    "tribeId": 100245,
    "color": "#4659df"
  },
  {
    "tribeId": 100213,
    "color": "#f6768e"
  },
  {
    "tribeId": 100174,
    "color": "#aac82d"
  },
  {
    "tribeId": 1000029,
    "color": "#554d15"
  },
  {
    "tribeId": 100002,
    "color": "#803e75"
  },
  {
    "tribeId": 100280,
    "color": "#b32851"
  },
  {
    "tribeId": 100327,
    "color": "#2c5df9"
  },
  {
    "tribeId": 100233,
    "color": "#08b7f1"
  },
  {
    "tribeId": 100266,
    "color": "#271869"
  },
  {
    "tribeId": 100478,
    "color": "#d783ef"
  },
  {
    "tribeId": 100254,
    "color": "#f980da"
  },
  {
    "tribeId": 100358,
    "color": "#6c358a"
  },
  {
    "tribeId": 100054,
    "color": "#ff6800"
  },
  {
    "tribeId": 100279,
    "color": "#5104d9"
  },
  {
    "tribeId": 100134,
    "color": "#f13a13"
  },
  {
    "tribeId": 100429,
    "color": "#abfec1"
  },
  {
    "tribeId": 1000051,
    "color": "#375d3c"
  },
  {
    "tribeId": 100165,
    "color": "#ec1859"
  },
  {
    "tribeId": 100094,
    "color": "#8525c0"
  },
  {
    "tribeId": 1000019,
    "color": "#2df39c"
  },
  {
    "tribeId": 100138,
    "color": "#188af4"
  },
  {
    "tribeId": 100187,
    "color": "#aa293f"
  },
  {
    "tribeId": 100180,
    "color": "#712021"
  },
  {
    "tribeId": 100432,
    "color": "#934bd7"
  },
  {
    "tribeId": 1000031,
    "color": "#053d92"
  },
  {
    "tribeId": 100318,
    "color": "#a20448"
  },
  {
    "tribeId": 100314,
    "color": "#3a7f5d"
  },
  {
    "tribeId": 100153,
    "color": "#38d059"
  },
  {
    "tribeId": 100219,
    "color": "#b53900"
  },
  {
    "tribeId": 100136,
    "color": "#0f525e"
  },
  {
    "tribeId": 100306,
    "color": "#2ecb8c"
  },
  {
    "tribeId": 100476,
    "color": "#3d54aa"
  },
  {
    "tribeId": 100452,
    "color": "#94a5da"
  },
  {
    "tribeId": 100442,
    "color": "#993add"
  },
  {
    "tribeId": 100415,
    "color": "#a0a212"
  },
  {
    "tribeId": 100179,
    "color": "#63e6d9"
  },
  {
    "tribeId": 100192,
    "color": "#c5e220"
  },
  {
    "tribeId": 100224,
    "color": "#77f273"
  },
  {
    "tribeId": 100394,
    "color": "#3edfb8"
  },
  {
    "tribeId": 1000047,
    "color": "#9bf4ee"
  },
  {
    "tribeId": 100216,
    "color": "#93aa00"
  },
  {
    "tribeId": 1000023,
    "color": "#3f61cd"
  },
  {
    "tribeId": 100325,
    "color": "#c2657e"
  },
  {
    "tribeId": 100399,
    "color": "#4bc6e7"
  },
  {
    "tribeId": 100256,
    "color": "#e70d5e"
  },
  {
    "tribeId": 100013,
    "color": "#6da045"
  },
  {
    "tribeId": 100386,
    "color": "#7f962d"
  },
  {
    "tribeId": 1000053,
    "color": "#475152"
  },
  {
    "tribeId": 100210,
    "color": "#25486f"
  },
  {
    "tribeId": 100244,
    "color": "#3db6d8"
  },
  {
    "tribeId": 100008,
    "color": "#18fe74"
  },
  {
    "tribeId": 100261,
    "color": "#f0f8af"
  },
  {
    "tribeId": 100477,
    "color": "#eb5ad7"
  },
  {
    "tribeId": 100292,
    "color": "#0fdd3d"
  },
  {
    "tribeId": 100191,
    "color": "#921820"
  },
  {
    "tribeId": 100122,
    "color": "#f0ddd4"
  },
  {
    "tribeId": 100235,
    "color": "#c10a52"
  },
  {
    "tribeId": 100162,
    "color": "#2ebd48"
  },
  {
    "tribeId": 100234,
    "color": "#8b53a2"
  },
  {
    "tribeId": 100252,
    "color": "#9c1919"
  },
  {
    "tribeId": 100264,
    "color": "#5d85ad"
  },
  {
    "tribeId": 100298,
    "color": "#a433c7"
  },
  {
    "tribeId": 100288,
    "color": "#73f514"
  },
  {
    "tribeId": 100246,
    "color": "#ad8145"
  },
  {
    "tribeId": 100076,
    "color": "#6c6fb8"
  },
  {
    "tribeId": 100081,
    "color": "#eeb339"
  },
  {
    "tribeId": 100156,
    "color": "#31346a"
  },
  {
    "tribeId": 100437,
    "color": "#9a7aac"
  },
  {
    "tribeId": 100355,
    "color": "#86e840"
  },
  {
    "tribeId": 100290,
    "color": "#2c65a4"
  },
  {
    "tribeId": 100380,
    "color": "#0c4f40"
  },
  {
    "tribeId": 100354,
    "color": "#beb158"
  },
  {
    "tribeId": 100104,
    "color": "#8eece3"
  },
  {
    "tribeId": 100253,
    "color": "#577de7"
  },
  {
    "tribeId": 100250,
    "color": "#bf1487"
  },
  {
    "tribeId": 1000065,
    "color": "#0cc04e"
  },
  {
    "tribeId": 100178,
    "color": "#8e9b9f"
  },
  {
    "tribeId": 100058,
    "color": "#ff7a5c"
  },
  {
    "tribeId": 100177,
    "color": "#696ae4"
  },
  {
    "tribeId": 100356,
    "color": "#adc20a"
  },
  {
    "tribeId": 100140,
    "color": "#011e49"
  },
  {
    "tribeId": 100077,
    "color": "#87468f"
  },
  {
    "tribeId": 1000025,
    "color": "#6fa032"
  },
  {
    "tribeId": 1000059,
    "color": "#05adbd"
  },
  {
    "tribeId": 100160,
    "color": "#605fc5"
  },
  {
    "tribeId": 100171,
    "color": "#54d9b5"
  },
  {
    "tribeId": 100036,
    "color": "#81d966"
  },
  {
    "tribeId": 100366,
    "color": "#247a28"
  },
  {
    "tribeId": 100295,
    "color": "#f09cc8"
  },
  {
    "tribeId": 100275,
    "color": "#04a2e3"
  },
  {
    "tribeId": 100400,
    "color": "#5b10ed"
  },
  {
    "tribeId": 100222,
    "color": "#4d8dce"
  },
  {
    "tribeId": 100066,
    "color": "#99cf36"
  },
  {
    "tribeId": 100024,
    "color": "#575072"
  },
  {
    "tribeId": 100350,
    "color": "#550613"
  },
  {
    "tribeId": 1000041,
    "color": "#8f2e3b"
  },
  {
    "tribeId": 100278,
    "color": "#d8148f"
  },
  {
    "tribeId": 100406,
    "color": "#2e2ce8"
  },
  {
    "tribeId": 100062,
    "color": "#a3dca2"
  },
  {
    "tribeId": 1000075,
    "color": "#2195a9"
  },
  {
    "tribeId": 1000054,
    "color": "#c56afd"
  },
  {
    "tribeId": 100349,
    "color": "#4da99c"
  },
  {
    "tribeId": 100363,
    "color": "#cf12d1"
  },
  {
    "tribeId": 100123,
    "color": "#7f180d"
  },
  {
    "tribeId": 100073,
    "color": "#f5b909"
  },
  {
    "tribeId": 100240,
    "color": "#7e2a88"
  },
  {
    "tribeId": 100142,
    "color": "#f2cd73"
  },
  {
    "tribeId": 100304,
    "color": "#817066"
  },
  {
    "tribeId": 100347,
    "color": "#14616e"
  },
  {
    "tribeId": 100017,
    "color": "#8d2b8d"
  },
  {
    "tribeId": 100112,
    "color": "#532ce3"
  },
  {
    "tribeId": 1000014,
    "color": "#04a9af"
  },
  {
    "tribeId": 100259,
    "color": "#2c783a"
  },
  {
    "tribeId": 100427,
    "color": "#8c90e5"
  },
  {
    "tribeId": 100135,
    "color": "#73085c"
  },
  {
    "tribeId": 100125,
    "color": "#75bf1b"
  },
  {
    "tribeId": 100060,
    "color": "#68e259"
  },
  {
    "tribeId": 100316,
    "color": "#86af01"
  },
  {
    "tribeId": 100168,
    "color": "#60af0f"
  },
  {
    "tribeId": 100087,
    "color": "#2e0c34"
  },
  {
    "tribeId": 100004,
    "color": "#3a383f"
  },
  {
    "tribeId": 100031,
    "color": "#70f87d"
  },
  {
    "tribeId": 100258,
    "color": "#b8ca68"
  },
  {
    "tribeId": 100346,
    "color": "#21c941"
  },
  {
    "tribeId": 100396,
    "color": "#cef098"
  },
  {
    "tribeId": 100342,
    "color": "#a27fc4"
  },
  {
    "tribeId": 100132,
    "color": "#179ea0"
  },
  {
    "tribeId": 100211,
    "color": "#522447"
  },
  {
    "tribeId": 100052,
    "color": "#33cc7c"
  },
  {
    "tribeId": 100487,
    "color": "#e1a3f8"
  },
  {
    "tribeId": 100018,
    "color": "#a0fc6b"
  },
  {
    "tribeId": 100080,
    "color": "#065257"
  },
  {
    "tribeId": 100044,
    "color": "#a6030f"
  },
  {
    "tribeId": 100370,
    "color": "#debbf4"
  },
  {
    "tribeId": 100383,
    "color": "#b14719"
  },
  {
    "tribeId": 100281,
    "color": "#18b7bd"
  },
  {
    "tribeId": 100078,
    "color": "#67bd30"
  },
  {
    "tribeId": 100009,
    "color": "#49176d"
  },
  {
    "tribeId": 1000020,
    "color": "#92e614"
  },
  {
    "tribeId": 100046,
    "color": "#f63c2b"
  },
  {
    "tribeId": 100286,
    "color": "#01d526"
  },
  {
    "tribeId": 100221,
    "color": "#6e80cb"
  },
  {
    "tribeId": 100200,
    "color": "#d5c79e"
  },
  {
    "tribeId": 100384,
    "color": "#41fa7b"
  },
  {
    "tribeId": 1000056,
    "color": "#b537e1"
  },
  {
    "tribeId": 100032,
    "color": "#aba0dc"
  },
  {
    "tribeId": 100248,
    "color": "#2e1b15"
  },
  {
    "tribeId": 100227,
    "color": "#bd7ae5"
  },
  {
    "tribeId": 100289,
    "color": "#c856e4"
  },
  {
    "tribeId": 100373,
    "color": "#fc726a"
  },
  {
    "tribeId": 100014,
    "color": "#43aec5"
  },
  {
    "tribeId": 100064,
    "color": "#e3dde5"
  },
  {
    "tribeId": 100409,
    "color": "#ce42c5"
  },
  {
    "tribeId": 1000058,
    "color": "#4c42ee"
  },
  {
    "tribeId": 100193,
    "color": "#1e26c1"
  },
  {
    "tribeId": 100063,
    "color": "#b493de"
  },
  {
    "tribeId": 100348,
    "color": "#8ae646"
  },
  {
    "tribeId": 100368,
    "color": "#37c721"
  },
  {
    "tribeId": 100117,
    "color": "#16425b"
  },
  {
    "tribeId": 100095,
    "color": "#3fa529"
  },
  {
    "tribeId": 100128,
    "color": "#e5d755"
  },
  {
    "tribeId": 100184,
    "color": "#34fc4c"
  },
  {
    "tribeId": 100488,
    "color": "#b4d159"
  },
  {
    "tribeId": 100340,
    "color": "#fbdb5d"
  },
  {
    "tribeId": 1000036,
    "color": "#16e1d7"
  },
  {
    "tribeId": 100106,
    "color": "#269f53"
  },
  {
    "tribeId": 100451,
    "color": "#2414c2"
  },
  {
    "tribeId": 100172,
    "color": "#06728b"
  },
  {
    "tribeId": 1000073,
    "color": "#230ce5"
  },
  {
    "tribeId": 100379,
    "color": "#a4cc9b"
  },
  {
    "tribeId": 100239,
    "color": "#898e9b"
  },
  {
    "tribeId": 100291,
    "color": "#9c656a"
  },
  {
    "tribeId": 100035,
    "color": "#99e828"
  },
  {
    "tribeId": 1000069,
    "color": "#74fec1"
  },
  {
    "tribeId": 100455,
    "color": "#858e0a"
  },
  {
    "tribeId": 100139,
    "color": "#e720e5"
  },
  {
    "tribeId": 100336,
    "color": "#48eea1"
  },
  {
    "tribeId": 100411,
    "color": "#071b91"
  },
  {
    "tribeId": 100242,
    "color": "#65df65"
  },
  {
    "tribeId": 100148,
    "color": "#c810f0"
  },
  {
    "tribeId": 100145,
    "color": "#651004"
  },
  {
    "tribeId": 100466,
    "color": "#bd714d"
  },
  {
    "tribeId": 100334,
    "color": "#c0797b"
  },
  {
    "tribeId": 100322,
    "color": "#6d8bb6"
  },
  {
    "tribeId": 100057,
    "color": "#2aae14"
  },
  {
    "tribeId": 100051,
    "color": "#007fe2"
  },
  {
    "tribeId": 100482,
    "color": "#803bea"
  },
  {
    "tribeId": 100268,
    "color": "#005bdd"
  },
  {
    "tribeId": 1000078,
    "color": "#f88273"
  },
  {
    "tribeId": 100204,
    "color": "#0a3684"
  },
  {
    "tribeId": 100317,
    "color": "#04cfd7"
  },
  {
    "tribeId": 100407,
    "color": "#370fee"
  },
  {
    "tribeId": 100282,
    "color": "#bdc61d"
  },
  {
    "tribeId": 100486,
    "color": "#bb26a6"
  },
  {
    "tribeId": 100301,
    "color": "#69d962"
  },
  {
    "tribeId": 100362,
    "color": "#e9db6b"
  },
  {
    "tribeId": 100311,
    "color": "#7c655f"
  },
  {
    "tribeId": 100126,
    "color": "#8147d4"
  },
  {
    "tribeId": 100357,
    "color": "#0565b3"
  },
  {
    "tribeId": 1000060,
    "color": "#26c3ed"
  },
  {
    "tribeId": 100161,
    "color": "#d9b642"
  },
  {
    "tribeId": 100294,
    "color": "#f568bb"
  },
  {
    "tribeId": 100446,
    "color": "#ddf29f"
  },
  {
    "tribeId": 100393,
    "color": "#2542b8"
  },
  {
    "tribeId": 100209,
    "color": "#c4c314"
  },
  {
    "tribeId": 1000062,
    "color": "#449580"
  },
  {
    "tribeId": 1000055,
    "color": "#7a0ea5"
  },
  {
    "tribeId": 100223,
    "color": "#078dd0"
  },
  {
    "tribeId": 1000026,
    "color": "#258188"
  },
  {
    "tribeId": 100214,
    "color": "#0232a9"
  },
  {
    "tribeId": 100196,
    "color": "#3a9702"
  },
  {
    "tribeId": 100232,
    "color": "#2ee16f"
  },
  {
    "tribeId": 100181,
    "color": "#637370"
  },
  {
    "tribeId": 100439,
    "color": "#a60ce8"
  },
  {
    "tribeId": 100391,
    "color": "#ca5622"
  },
  {
    "tribeId": 100436,
    "color": "#a6bc82"
  },
  {
    "tribeId": 100320,
    "color": "#bfbfcf"
  },
  {
    "tribeId": 100472,
    "color": "#33abb5"
  },
  {
    "tribeId": 100475,
    "color": "#48d129"
  }
]