[
  {
    "tribeId": 100038,
    "color": "#b4beea"
  },
  {
    "tribeId": 100328,
    "color": "#26132a"
  },
  {
    "tribeId": 100205,
    "color": "#593315"
  },
  {
    "tribeId": 100272,
    "color": "#53377a"
  },
  {
    "tribeId": 100167,
    "color": "#c10020"
  },
  {
    "tribeId": 100195,
    "color": "#2f722c"
  },
  {
    "tribeId": 100025,
    "color": "#ff8e00"
  },
  {
    "tribeId": 100061,
    "color": "#a6bdd7"
  },
  {
    "tribeId": 1000024,
    "color": "#e29818"
  },
  {
    "tribeId": 100371,
    "color": "#ac00a7"
  },
  {
    "tribeId": 100375,
    "color": "#00538a"
  },
  {
    "tribeId": 100048,
    "color": "#cea262"
  },
  {
    "tribeId": 100213,
    "color": "#f6768e"
  },
  {
    "tribeId": 1000063,
    "color": "#83fc72"
  },
  {
    "tribeId": 100190,
    "color": "#007d34"
  },
  {
    "tribeId": 100364,
    "color": "#6549b9"
  },
  {
    "tribeId": 100293,
    "color": "#232c16"
  },
  {
    "tribeId": 100351,
    "color": "#adcb6f"
  },
  {
    "tribeId": 100241,
    "color": "#7d83cf"
  },
  {
    "tribeId": 100218,
    "color": "#0d319d"
  },
  {
    "tribeId": 100249,
    "color": "#f4c800"
  },
  {
    "tribeId": 1000066,
    "color": "#985279"
  },
  {
    "tribeId": 100308,
    "color": "#1f7ff1"
  },
  {
    "tribeId": 100372,
    "color": "#c51d2b"
  },
  {
    "tribeId": 100245,
    "color": "#6f3f95"
  },
  {
    "tribeId": 100134,
    "color": "#f13a13"
  },
  {
    "tribeId": 100174,
    "color": "#70f6ac"
  },
  {
    "tribeId": 1000029,
    "color": "#4635e4"
  },
  {
    "tribeId": 100002,
    "color": "#803e75"
  },
  {
    "tribeId": 100280,
    "color": "#b32851"
  },
  {
    "tribeId": 100327,
    "color": "#dfee58"
  },
  {
    "tribeId": 100233,
    "color": "#692f36"
  },
  {
    "tribeId": 100266,
    "color": "#6506f1"
  },
  {
    "tribeId": 100478,
    "color": "#7ba78e"
  },
  {
    "tribeId": 100254,
    "color": "#5a2241"
  },
  {
    "tribeId": 100358,
    "color": "#8d4a45"
  },
  {
    "tribeId": 100054,
    "color": "#ff6800"
  },
  {
    "tribeId": 100279,
    "color": "#9d8d7f"
  },
  {
    "tribeId": 100429,
    "color": "#b4bcdf"
  },
  {
    "tribeId": 1000051,
    "color": "#47f409"
  },
  {
    "tribeId": 1000076,
    "color": "#233dd4"
  },
  {
    "tribeId": 100165,
    "color": "#c1364d"
  },
  {
    "tribeId": 100094,
    "color": "#ea2c42"
  },
  {
    "tribeId": 1000019,
    "color": "#452f23"
  },
  {
    "tribeId": 100153,
    "color": "#42b879"
  },
  {
    "tribeId": 100138,
    "color": "#fe4974"
  },
  {
    "tribeId": 100187,
    "color": "#9b151d"
  },
  {
    "tribeId": 100180,
    "color": "#54e1ac"
  },
  {
    "tribeId": 100432,
    "color": "#67a8a7"
  },
  {
    "tribeId": 1000031,
    "color": "#642a31"
  },
  {
    "tribeId": 100318,
    "color": "#772239"
  },
  {
    "tribeId": 100314,
    "color": "#2d41c8"
  },
  {
    "tribeId": 100219,
    "color": "#1db970"
  },
  {
    "tribeId": 100136,
    "color": "#406ef4"
  },
  {
    "tribeId": 100306,
    "color": "#fd481a"
  },
  {
    "tribeId": 100476,
    "color": "#225bd3"
  },
  {
    "tribeId": 100452,
    "color": "#06b573"
  },
  {
    "tribeId": 100442,
    "color": "#6aaadf"
  },
  {
    "tribeId": 100415,
    "color": "#eace5a"
  },
  {
    "tribeId": 100179,
    "color": "#28598d"
  },
  {
    "tribeId": 100192,
    "color": "#a58502"
  },
  {
    "tribeId": 100224,
    "color": "#11cd0d"
  },
  {
    "tribeId": 100394,
    "color": "#e81576"
  },
  {
    "tribeId": 1000047,
    "color": "#afe18e"
  },
  {
    "tribeId": 100216,
    "color": "#93aa00"
  },
  {
    "tribeId": 1000023,
    "color": "#045aa5"
  },
  {
    "tribeId": 100325,
    "color": "#285699"
  },
  {
    "tribeId": 100399,
    "color": "#91444d"
  },
  {
    "tribeId": 100256,
    "color": "#d35e73"
  },
  {
    "tribeId": 100013,
    "color": "#ffb300"
  },
  {
    "tribeId": 100386,
    "color": "#bd0c76"
  },
  {
    "tribeId": 1000053,
    "color": "#584272"
  },
  {
    "tribeId": 100210,
    "color": "#6df45f"
  },
  {
    "tribeId": 100244,
    "color": "#e19ae7"
  },
  {
    "tribeId": 100008,
    "color": "#f1eb79"
  },
  {
    "tribeId": 100261,
    "color": "#0d3846"
  },
  {
    "tribeId": 100477,
    "color": "#5c55d2"
  },
  {
    "tribeId": 100292,
    "color": "#e3664f"
  },
  {
    "tribeId": 100191,
    "color": "#3ac177"
  },
  {
    "tribeId": 100122,
    "color": "#c09515"
  },
  {
    "tribeId": 100235,
    "color": "#40d127"
  },
  {
    "tribeId": 100162,
    "color": "#8d53c0"
  },
  {
    "tribeId": 100234,
    "color": "#958fd1"
  },
  {
    "tribeId": 100252,
    "color": "#0442eb"
  },
  {
    "tribeId": 100264,
    "color": "#2e21be"
  },
  {
    "tribeId": 100298,
    "color": "#bc3669"
  },
  {
    "tribeId": 100288,
    "color": "#1f840b"
  },
  {
    "tribeId": 100246,
    "color": "#067608"
  },
  {
    "tribeId": 100076,
    "color": "#9fd8a4"
  },
  {
    "tribeId": 100081,
    "color": "#271e7f"
  },
  {
    "tribeId": 100156,
    "color": "#f9ac5e"
  },
  {
    "tribeId": 100437,
    "color": "#4aa0c8"
  },
  {
    "tribeId": 100355,
    "color": "#c06398"
  },
  {
    "tribeId": 100290,
    "color": "#b876a7"
  },
  {
    "tribeId": 100380,
    "color": "#735813"
  },
  {
    "tribeId": 100354,
    "color": "#e6b445"
  },
  {
    "tribeId": 100104,
    "color": "#8f7d8b"
  },
  {
    "tribeId": 100253,
    "color": "#0ea011"
  },
  {
    "tribeId": 100250,
    "color": "#09395a"
  },
  {
    "tribeId": 1000065,
    "color": "#1eed79"
  },
  {
    "tribeId": 100178,
    "color": "#1b6e71"
  },
  {
    "tribeId": 100058,
    "color": "#ff7a5c"
  },
  {
    "tribeId": 100177,
    "color": "#520a94"
  },
  {
    "tribeId": 100356,
    "color": "#8de27f"
  },
  {
    "tribeId": 100140,
    "color": "#f5fad1"
  },
  {
    "tribeId": 100077,
    "color": "#d0660d"
  },
  {
    "tribeId": 1000025,
    "color": "#62921e"
  },
  {
    "tribeId": 1000059,
    "color": "#f4b824"
  },
  {
    "tribeId": 100160,
    "color": "#5f969f"
  },
  {
    "tribeId": 100171,
    "color": "#f2eb0c"
  },
  {
    "tribeId": 100036,
    "color": "#4d4167"
  },
  {
    "tribeId": 100366,
    "color": "#6da175"
  },
  {
    "tribeId": 100295,
    "color": "#1f9c08"
  },
  {
    "tribeId": 100275,
    "color": "#36204d"
  },
  {
    "tribeId": 100400,
    "color": "#7d59d0"
  },
  {
    "tribeId": 100222,
    "color": "#c59981"
  },
  {
    "tribeId": 100066,
    "color": "#b83d3a"
  },
  {
    "tribeId": 100024,
    "color": "#04a5a5"
  },
  {
    "tribeId": 100350,
    "color": "#3c2934"
  },
  {
    "tribeId": 1000041,
    "color": "#55bad7"
  },
  {
    "tribeId": 100278,
    "color": "#d05e1d"
  },
  {
    "tribeId": 100406,
    "color": "#883fa1"
  },
  {
    "tribeId": 100062,
    "color": "#188759"
  },
  {
    "tribeId": 1000075,
    "color": "#5cb0c8"
  },
  {
    "tribeId": 1000054,
    "color": "#042c72"
  },
  {
    "tribeId": 100349,
    "color": "#cf765f"
  },
  {
    "tribeId": 100363,
    "color": "#5299fc"
  },
  {
    "tribeId": 100123,
    "color": "#7f180d"
  },
  {
    "tribeId": 100073,
    "color": "#1e3aae"
  },
  {
    "tribeId": 100240,
    "color": "#d1499b"
  },
  {
    "tribeId": 100142,
    "color": "#c03177"
  },
  {
    "tribeId": 100304,
    "color": "#817066"
  },
  {
    "tribeId": 100347,
    "color": "#41c9e0"
  },
  {
    "tribeId": 100017,
    "color": "#3064c1"
  },
  {
    "tribeId": 100112,
    "color": "#30f419"
  },
  {
    "tribeId": 1000014,
    "color": "#2fac11"
  },
  {
    "tribeId": 100259,
    "color": "#275c8b"
  },
  {
    "tribeId": 100427,
    "color": "#70fe78"
  },
  {
    "tribeId": 100135,
    "color": "#336bb1"
  },
  {
    "tribeId": 100125,
    "color": "#d30221"
  },
  {
    "tribeId": 100060,
    "color": "#d9b224"
  },
  {
    "tribeId": 100316,
    "color": "#6eb5f4"
  },
  {
    "tribeId": 100168,
    "color": "#055756"
  },
  {
    "tribeId": 100087,
    "color": "#e01be6"
  },
  {
    "tribeId": 100004,
    "color": "#e6d3c7"
  },
  {
    "tribeId": 100031,
    "color": "#b09f81"
  },
  {
    "tribeId": 100258,
    "color": "#4622eb"
  },
  {
    "tribeId": 100346,
    "color": "#eaf5dc"
  },
  {
    "tribeId": 100396,
    "color": "#23604a"
  },
  {
    "tribeId": 100342,
    "color": "#228cc4"
  },
  {
    "tribeId": 100132,
    "color": "#c56cc6"
  },
  {
    "tribeId": 100211,
    "color": "#bf55b0"
  },
  {
    "tribeId": 100052,
    "color": "#9cc03f"
  },
  {
    "tribeId": 100487,
    "color": "#232955"
  },
  {
    "tribeId": 100018,
    "color": "#ba4541"
  },
  {
    "tribeId": 100080,
    "color": "#a3892a"
  },
  {
    "tribeId": 100044,
    "color": "#b082cb"
  },
  {
    "tribeId": 100370,
    "color": "#308dde"
  },
  {
    "tribeId": 100383,
    "color": "#34eebb"
  },
  {
    "tribeId": 100281,
    "color": "#464b54"
  },
  {
    "tribeId": 100078,
    "color": "#aae2c9"
  },
  {
    "tribeId": 100009,
    "color": "#901bad"
  },
  {
    "tribeId": 1000020,
    "color": "#20267e"
  },
  {
    "tribeId": 100046,
    "color": "#1613dd"
  },
  {
    "tribeId": 100286,
    "color": "#4222f8"
  },
  {
    "tribeId": 100221,
    "color": "#962fb0"
  },
  {
    "tribeId": 100200,
    "color": "#9b7ed6"
  },
  {
    "tribeId": 100384,
    "color": "#207009"
  },
  {
    "tribeId": 1000056,
    "color": "#f795de"
  },
  {
    "tribeId": 100032,
    "color": "#e68b66"
  },
  {
    "tribeId": 100248,
    "color": "#f45675"
  },
  {
    "tribeId": 100227,
    "color": "#e97846"
  },
  {
    "tribeId": 100289,
    "color": "#8a2a2a"
  },
  {
    "tribeId": 100373,
    "color": "#938362"
  },
  {
    "tribeId": 100014,
    "color": "#ab9a6f"
  },
  {
    "tribeId": 100064,
    "color": "#eded6b"
  },
  {
    "tribeId": 100409,
    "color": "#e59dbe"
  },
  {
    "tribeId": 1000058,
    "color": "#0ba9cc"
  },
  {
    "tribeId": 100193,
    "color": "#7d8a71"
  },
  {
    "tribeId": 100063,
    "color": "#bf9785"
  },
  {
    "tribeId": 100348,
    "color": "#cd389a"
  },
  {
    "tribeId": 100368,
    "color": "#1720bb"
  },
  {
    "tribeId": 100117,
    "color": "#6858a8"
  },
  {
    "tribeId": 100095,
    "color": "#b20b05"
  },
  {
    "tribeId": 100128,
    "color": "#8508f9"
  },
  {
    "tribeId": 100184,
    "color": "#7473d5"
  },
  {
    "tribeId": 100488,
    "color": "#990aa7"
  },
  {
    "tribeId": 100340,
    "color": "#7301ec"
  },
  {
    "tribeId": 1000036,
    "color": "#a6e9ab"
  },
  {
    "tribeId": 100106,
    "color": "#a86bed"
  },
  {
    "tribeId": 100451,
    "color": "#d3ca91"
  },
  {
    "tribeId": 100172,
    "color": "#a4c44b"
  },
  {
    "tribeId": 1000073,
    "color": "#c69379"
  },
  {
    "tribeId": 100379,
    "color": "#b28595"
  },
  {
    "tribeId": 100239,
    "color": "#c13392"
  },
  {
    "tribeId": 100291,
    "color": "#b884a1"
  },
  {
    "tribeId": 100035,
    "color": "#d10916"
  },
  {
    "tribeId": 1000069,
    "color": "#9b268d"
  },
  {
    "tribeId": 100455,
    "color": "#dc5936"
  },
  {
    "tribeId": 100139,
    "color": "#ad7036"
  },
  {
    "tribeId": 100336,
    "color": "#0fbeeb"
  },
  {
    "tribeId": 100411,
    "color": "#b9dd3f"
  },
  {
    "tribeId": 100242,
    "color": "#73df42"
  },
  {
    "tribeId": 100148,
    "color": "#aeacdf"
  },
  {
    "tribeId": 100145,
    "color": "#5be684"
  },
  {
    "tribeId": 100466,
    "color": "#11b1cc"
  },
  {
    "tribeId": 100334,
    "color": "#5aed64"
  },
  {
    "tribeId": 100322,
    "color": "#0ad662"
  },
  {
    "tribeId": 100057,
    "color": "#d737a4"
  },
  {
    "tribeId": 100051,
    "color": "#04c66a"
  },
  {
    "tribeId": 100482,
    "color": "#141923"
  },
  {
    "tribeId": 100268,
    "color": "#42a2c5"
  },
  {
    "tribeId": 1000078,
    "color": "#a80754"
  },
  {
    "tribeId": 100204,
    "color": "#5245a4"
  },
  {
    "tribeId": 100317,
    "color": "#5e225b"
  },
  {
    "tribeId": 100407,
    "color": "#353f3f"
  },
  {
    "tribeId": 100282,
    "color": "#09caa7"
  },
  {
    "tribeId": 100486,
    "color": "#685281"
  },
  {
    "tribeId": 100301,
    "color": "#d104e7"
  },
  {
    "tribeId": 100362,
    "color": "#88e1a6"
  },
  {
    "tribeId": 100311,
    "color": "#9a6f19"
  },
  {
    "tribeId": 100126,
    "color": "#d69992"
  },
  {
    "tribeId": 100357,
    "color": "#bc1943"
  },
  {
    "tribeId": 1000060,
    "color": "#bd68a9"
  },
  {
    "tribeId": 100161,
    "color": "#7808a7"
  },
  {
    "tribeId": 100294,
    "color": "#bfabb3"
  },
  {
    "tribeId": 100446,
    "color": "#06a1f7"
  },
  {
    "tribeId": 100393,
    "color": "#64f9fa"
  },
  {
    "tribeId": 100209,
    "color": "#c2aac6"
  },
  {
    "tribeId": 1000062,
    "color": "#a0709d"
  },
  {
    "tribeId": 1000055,
    "color": "#dc2025"
  },
  {
    "tribeId": 100223,
    "color": "#adb6d5"
  },
  {
    "tribeId": 1000026,
    "color": "#8b8687"
  },
  {
    "tribeId": 100214,
    "color": "#c77826"
  },
  {
    "tribeId": 100196,
    "color": "#fa4a62"
  },
  {
    "tribeId": 100232,
    "color": "#fdef49"
  },
  {
    "tribeId": 100181,
    "color": "#d91258"
  },
  {
    "tribeId": 100439,
    "color": "#34813f"
  },
  {
    "tribeId": 100391,
    "color": "#ad3574"
  },
  {
    "tribeId": 100436,
    "color": "#1d14ee"
  },
  {
    "tribeId": 100320,
    "color": "#cb1ba7"
  },
  {
    "tribeId": 100472,
    "color": "#a4df47"
  },
  {
    "tribeId": 100475,
    "color": "#83c951"
  }
]