[
  {
    "tribeId": 100038,
    "color": "#f27a62"
  },
  {
    "tribeId": 100328,
    "color": "#089662"
  },
  {
    "tribeId": 100205,
    "color": "#593315"
  },
  {
    "tribeId": 100249,
    "color": "#f4c800"
  },
  {
    "tribeId": 1000076,
    "color": "#ce476e"
  },
  {
    "tribeId": 100167,
    "color": "#c10020"
  },
  {
    "tribeId": 100195,
    "color": "#ffb300"
  },
  {
    "tribeId": 100025,
    "color": "#ff8e00"
  },
  {
    "tribeId": 100061,
    "color": "#a6bdd7"
  },
  {
    "tribeId": 1000024,
    "color": "#edd501"
  },
  {
    "tribeId": 100371,
    "color": "#56bd6a"
  },
  {
    "tribeId": 100375,
    "color": "#00538a"
  },
  {
    "tribeId": 100048,
    "color": "#cea262"
  },
  {
    "tribeId": 100213,
    "color": "#f6768e"
  },
  {
    "tribeId": 1000063,
    "color": "#3b8e44"
  },
  {
    "tribeId": 100190,
    "color": "#007d34"
  },
  {
    "tribeId": 100364,
    "color": "#bea284"
  },
  {
    "tribeId": 100351,
    "color": "#21be98"
  },
  {
    "tribeId": 100241,
    "color": "#bdbeaa"
  },
  {
    "tribeId": 1000066,
    "color": "#18b8d8"
  },
  {
    "tribeId": 100272,
    "color": "#72af3a"
  },
  {
    "tribeId": 100308,
    "color": "#daf571"
  },
  {
    "tribeId": 100372,
    "color": "#3fde6c"
  },
  {
    "tribeId": 100245,
    "color": "#a47ce1"
  },
  {
    "tribeId": 100153,
    "color": "#da13d4"
  },
  {
    "tribeId": 100293,
    "color": "#f4e815"
  },
  {
    "tribeId": 100174,
    "color": "#a3a9a0"
  },
  {
    "tribeId": 1000029,
    "color": "#140c44"
  },
  {
    "tribeId": 100002,
    "color": "#803e75"
  },
  {
    "tribeId": 100280,
    "color": "#b32851"
  },
  {
    "tribeId": 100327,
    "color": "#32d1ba"
  },
  {
    "tribeId": 100233,
    "color": "#c949d6"
  },
  {
    "tribeId": 100266,
    "color": "#b7b58e"
  },
  {
    "tribeId": 100478,
    "color": "#947a25"
  },
  {
    "tribeId": 100254,
    "color": "#c57ac6"
  },
  {
    "tribeId": 100358,
    "color": "#f7faaf"
  },
  {
    "tribeId": 100054,
    "color": "#ff6800"
  },
  {
    "tribeId": 100279,
    "color": "#d61a26"
  },
  {
    "tribeId": 100134,
    "color": "#f13a13"
  },
  {
    "tribeId": 100429,
    "color": "#a246aa"
  },
  {
    "tribeId": 1000051,
    "color": "#c2c8d4"
  },
  {
    "tribeId": 100165,
    "color": "#94740e"
  },
  {
    "tribeId": 100094,
    "color": "#385ea2"
  },
  {
    "tribeId": 1000019,
    "color": "#f5a824"
  },
  {
    "tribeId": 100218,
    "color": "#b57594"
  },
  {
    "tribeId": 100138,
    "color": "#95ebc5"
  },
  {
    "tribeId": 100187,
    "color": "#534597"
  },
  {
    "tribeId": 100180,
    "color": "#ae2e6e"
  },
  {
    "tribeId": 100432,
    "color": "#4eaaad"
  },
  {
    "tribeId": 1000031,
    "color": "#ef3cf1"
  },
  {
    "tribeId": 100318,
    "color": "#1d8f8b"
  },
  {
    "tribeId": 100314,
    "color": "#0f0680"
  },
  {
    "tribeId": 100219,
    "color": "#022241"
  },
  {
    "tribeId": 100136,
    "color": "#7f5c1c"
  },
  {
    "tribeId": 100306,
    "color": "#81ced0"
  },
  {
    "tribeId": 100476,
    "color": "#a14184"
  },
  {
    "tribeId": 100452,
    "color": "#1a412d"
  },
  {
    "tribeId": 100442,
    "color": "#5f4f01"
  },
  {
    "tribeId": 100415,
    "color": "#13149a"
  },
  {
    "tribeId": 100179,
    "color": "#6546c8"
  },
  {
    "tribeId": 100192,
    "color": "#5f4721"
  },
  {
    "tribeId": 100224,
    "color": "#b0d719"
  },
  {
    "tribeId": 100394,
    "color": "#98a66f"
  },
  {
    "tribeId": 1000047,
    "color": "#1492c8"
  },
  {
    "tribeId": 100216,
    "color": "#93aa00"
  },
  {
    "tribeId": 1000023,
    "color": "#84d2e7"
  },
  {
    "tribeId": 100325,
    "color": "#7b2c5e"
  },
  {
    "tribeId": 100399,
    "color": "#9cab68"
  },
  {
    "tribeId": 100256,
    "color": "#29d5f9"
  },
  {
    "tribeId": 100013,
    "color": "#53377a"
  },
  {
    "tribeId": 100386,
    "color": "#c4bd3f"
  },
  {
    "tribeId": 1000053,
    "color": "#89fbf0"
  },
  {
    "tribeId": 100210,
    "color": "#e59bdb"
  },
  {
    "tribeId": 100244,
    "color": "#771f15"
  },
  {
    "tribeId": 100008,
    "color": "#fad0f5"
  },
  {
    "tribeId": 100261,
    "color": "#b7099a"
  },
  {
    "tribeId": 100477,
    "color": "#1405ae"
  },
  {
    "tribeId": 100292,
    "color": "#63d97b"
  },
  {
    "tribeId": 100191,
    "color": "#1896e6"
  },
  {
    "tribeId": 100122,
    "color": "#3bc799"
  },
  {
    "tribeId": 100235,
    "color": "#603670"
  },
  {
    "tribeId": 100162,
    "color": "#26ea1a"
  },
  {
    "tribeId": 100234,
    "color": "#d80ea9"
  },
  {
    "tribeId": 100252,
    "color": "#7d2ef6"
  },
  {
    "tribeId": 100264,
    "color": "#ec0db3"
  },
  {
    "tribeId": 100298,
    "color": "#d2805a"
  },
  {
    "tribeId": 100288,
    "color": "#67e3a2"
  },
  {
    "tribeId": 100246,
    "color": "#cd14d0"
  },
  {
    "tribeId": 100076,
    "color": "#4b60e2"
  },
  {
    "tribeId": 100081,
    "color": "#c37165"
  },
  {
    "tribeId": 100156,
    "color": "#0aa9d2"
  },
  {
    "tribeId": 100437,
    "color": "#4117e7"
  },
  {
    "tribeId": 100355,
    "color": "#a3d4e4"
  },
  {
    "tribeId": 100290,
    "color": "#dbdef9"
  },
  {
    "tribeId": 100380,
    "color": "#f095d6"
  },
  {
    "tribeId": 100104,
    "color": "#b776cc"
  },
  {
    "tribeId": 100253,
    "color": "#c64416"
  },
  {
    "tribeId": 100250,
    "color": "#817066"
  },
  {
    "tribeId": 1000065,
    "color": "#8bd2e2"
  },
  {
    "tribeId": 100178,
    "color": "#f69222"
  },
  {
    "tribeId": 100058,
    "color": "#ff7a5c"
  },
  {
    "tribeId": 100177,
    "color": "#9fd98a"
  },
  {
    "tribeId": 100356,
    "color": "#36149b"
  },
  {
    "tribeId": 100140,
    "color": "#447383"
  },
  {
    "tribeId": 100077,
    "color": "#23aaf5"
  },
  {
    "tribeId": 1000025,
    "color": "#cb2fab"
  },
  {
    "tribeId": 1000059,
    "color": "#748b05"
  },
  {
    "tribeId": 100160,
    "color": "#a7db7d"
  },
  {
    "tribeId": 100171,
    "color": "#f893e9"
  },
  {
    "tribeId": 100036,
    "color": "#16fc2d"
  },
  {
    "tribeId": 100366,
    "color": "#4e7dd6"
  },
  {
    "tribeId": 100295,
    "color": "#ee4a83"
  },
  {
    "tribeId": 100275,
    "color": "#c403f9"
  },
  {
    "tribeId": 100400,
    "color": "#5aa4c9"
  },
  {
    "tribeId": 100222,
    "color": "#5eac22"
  },
  {
    "tribeId": 100066,
    "color": "#5293ca"
  },
  {
    "tribeId": 100024,
    "color": "#d6fa15"
  },
  {
    "tribeId": 100350,
    "color": "#6a1647"
  },
  {
    "tribeId": 1000041,
    "color": "#dd4fb5"
  },
  {
    "tribeId": 100278,
    "color": "#a4a646"
  },
  {
    "tribeId": 100406,
    "color": "#a02017"
  },
  {
    "tribeId": 100062,
    "color": "#6ef4f4"
  },
  {
    "tribeId": 1000075,
    "color": "#ab3360"
  },
  {
    "tribeId": 1000054,
    "color": "#71062b"
  },
  {
    "tribeId": 100349,
    "color": "#b01ae5"
  },
  {
    "tribeId": 100363,
    "color": "#3a492f"
  },
  {
    "tribeId": 100123,
    "color": "#7f180d"
  },
  {
    "tribeId": 100073,
    "color": "#5aa5fe"
  },
  {
    "tribeId": 100240,
    "color": "#1e3e01"
  },
  {
    "tribeId": 100142,
    "color": "#17e367"
  },
  {
    "tribeId": 100347,
    "color": "#8f11f9"
  },
  {
    "tribeId": 100017,
    "color": "#cd205c"
  },
  {
    "tribeId": 100112,
    "color": "#b3b984"
  },
  {
    "tribeId": 1000014,
    "color": "#b2eeb7"
  },
  {
    "tribeId": 100259,
    "color": "#2ca560"
  },
  {
    "tribeId": 100427,
    "color": "#6a65f3"
  },
  {
    "tribeId": 100135,
    "color": "#e8b8fb"
  },
  {
    "tribeId": 100125,
    "color": "#60a306"
  },
  {
    "tribeId": 100060,
    "color": "#864900"
  },
  {
    "tribeId": 100316,
    "color": "#4681e0"
  },
  {
    "tribeId": 100168,
    "color": "#155710"
  },
  {
    "tribeId": 100087,
    "color": "#8d1c22"
  },
  {
    "tribeId": 100004,
    "color": "#65a2e4"
  },
  {
    "tribeId": 100031,
    "color": "#cefc5f"
  },
  {
    "tribeId": 100354,
    "color": "#608759"
  },
  {
    "tribeId": 100258,
    "color": "#772efe"
  },
  {
    "tribeId": 100346,
    "color": "#9eb3d8"
  },
  {
    "tribeId": 100396,
    "color": "#0c2e2a"
  },
  {
    "tribeId": 100342,
    "color": "#6b2e6d"
  },
  {
    "tribeId": 100132,
    "color": "#f347d6"
  },
  {
    "tribeId": 100211,
    "color": "#5c6c38"
  },
  {
    "tribeId": 100052,
    "color": "#a39c97"
  },
  {
    "tribeId": 100487,
    "color": "#a69e89"
  },
  {
    "tribeId": 100018,
    "color": "#3d04c1"
  },
  {
    "tribeId": 100080,
    "color": "#0f1abb"
  },
  {
    "tribeId": 100044,
    "color": "#9b001b"
  },
  {
    "tribeId": 100370,
    "color": "#ab0f1a"
  },
  {
    "tribeId": 100383,
    "color": "#00a7cc"
  },
  {
    "tribeId": 100281,
    "color": "#070928"
  },
  {
    "tribeId": 100078,
    "color": "#e522ed"
  },
  {
    "tribeId": 100009,
    "color": "#b4715b"
  },
  {
    "tribeId": 1000020,
    "color": "#0e718f"
  },
  {
    "tribeId": 100046,
    "color": "#27bcea"
  },
  {
    "tribeId": 100286,
    "color": "#c1cf8f"
  },
  {
    "tribeId": 100304,
    "color": "#232c16"
  },
  {
    "tribeId": 100221,
    "color": "#7560af"
  },
  {
    "tribeId": 100200,
    "color": "#17fc13"
  },
  {
    "tribeId": 100384,
    "color": "#6dce2e"
  },
  {
    "tribeId": 1000056,
    "color": "#514737"
  },
  {
    "tribeId": 100032,
    "color": "#bb5bc4"
  },
  {
    "tribeId": 100248,
    "color": "#6a9c93"
  },
  {
    "tribeId": 100227,
    "color": "#6ec07b"
  },
  {
    "tribeId": 100289,
    "color": "#9b8891"
  },
  {
    "tribeId": 100373,
    "color": "#6500a7"
  },
  {
    "tribeId": 100014,
    "color": "#2c7443"
  },
  {
    "tribeId": 100064,
    "color": "#30e93e"
  },
  {
    "tribeId": 100409,
    "color": "#8a8a47"
  },
  {
    "tribeId": 1000058,
    "color": "#1def0b"
  },
  {
    "tribeId": 100193,
    "color": "#147752"
  },
  {
    "tribeId": 100063,
    "color": "#be632a"
  },
  {
    "tribeId": 100348,
    "color": "#235216"
  },
  {
    "tribeId": 100368,
    "color": "#cabc1f"
  },
  {
    "tribeId": 100117,
    "color": "#57530f"
  },
  {
    "tribeId": 100095,
    "color": "#13d9d6"
  },
  {
    "tribeId": 100128,
    "color": "#1db0fc"
  },
  {
    "tribeId": 100488,
    "color": "#6b415a"
  },
  {
    "tribeId": 100340,
    "color": "#ea205d"
  },
  {
    "tribeId": 1000036,
    "color": "#f830d0"
  },
  {
    "tribeId": 100106,
    "color": "#7c4cac"
  },
  {
    "tribeId": 100184,
    "color": "#875948"
  },
  {
    "tribeId": 100451,
    "color": "#29db25"
  },
  {
    "tribeId": 100172,
    "color": "#6741ad"
  },
  {
    "tribeId": 1000073,
    "color": "#9160b6"
  },
  {
    "tribeId": 100239,
    "color": "#23d896"
  },
  {
    "tribeId": 100291,
    "color": "#2f77af"
  },
  {
    "tribeId": 100035,
    "color": "#6f003e"
  },
  {
    "tribeId": 1000069,
    "color": "#0ea835"
  },
  {
    "tribeId": 100455,
    "color": "#f7d342"
  },
  {
    "tribeId": 100139,
    "color": "#cc2a21"
  },
  {
    "tribeId": 100336,
    "color": "#444d6f"
  },
  {
    "tribeId": 100411,
    "color": "#72cef8"
  },
  {
    "tribeId": 100242,
    "color": "#c5e9fc"
  },
  {
    "tribeId": 100148,
    "color": "#b0b46e"
  },
  {
    "tribeId": 100145,
    "color": "#4ed9df"
  },
  {
    "tribeId": 100466,
    "color": "#a2c647"
  },
  {
    "tribeId": 100334,
    "color": "#c5c8b8"
  },
  {
    "tribeId": 100322,
    "color": "#200c4b"
  },
  {
    "tribeId": 100057,
    "color": "#6d79b0"
  },
  {
    "tribeId": 100051,
    "color": "#123107"
  },
  {
    "tribeId": 100482,
    "color": "#e29a16"
  },
  {
    "tribeId": 100268,
    "color": "#8b4c13"
  },
  {
    "tribeId": 1000078,
    "color": "#46af09"
  },
  {
    "tribeId": 100204,
    "color": "#9c688d"
  },
  {
    "tribeId": 100317,
    "color": "#b1be4a"
  },
  {
    "tribeId": 100407,
    "color": "#cebecd"
  },
  {
    "tribeId": 100282,
    "color": "#55540c"
  },
  {
    "tribeId": 100486,
    "color": "#fa0661"
  },
  {
    "tribeId": 100301,
    "color": "#682340"
  },
  {
    "tribeId": 1000084,
    "color": "#240554"
  },
  {
    "tribeId": 100362,
    "color": "#48b2b7"
  },
  {
    "tribeId": 100311,
    "color": "#f5cd1a"
  },
  {
    "tribeId": 100126,
    "color": "#58c28d"
  },
  {
    "tribeId": 100357,
    "color": "#cc5b17"
  },
  {
    "tribeId": 1000060,
    "color": "#3d2960"
  },
  {
    "tribeId": 100161,
    "color": "#2a6d4d"
  },
  {
    "tribeId": 100294,
    "color": "#009eba"
  },
  {
    "tribeId": 100446,
    "color": "#e1bcdb"
  },
  {
    "tribeId": 100393,
    "color": "#f9e793"
  },
  {
    "tribeId": 100209,
    "color": "#b42228"
  },
  {
    "tribeId": 1000062,
    "color": "#d122aa"
  },
  {
    "tribeId": 1000055,
    "color": "#b454b4"
  },
  {
    "tribeId": 100223,
    "color": "#d4bbef"
  },
  {
    "tribeId": 1000026,
    "color": "#2f76fa"
  },
  {
    "tribeId": 100214,
    "color": "#4088f7"
  },
  {
    "tribeId": 100196,
    "color": "#f4bcdc"
  },
  {
    "tribeId": 100232,
    "color": "#013db4"
  },
  {
    "tribeId": 100181,
    "color": "#f22365"
  },
  {
    "tribeId": 100439,
    "color": "#9965f5"
  },
  {
    "tribeId": 100391,
    "color": "#dafae5"
  },
  {
    "tribeId": 100436,
    "color": "#85a29f"
  },
  {
    "tribeId": 100320,
    "color": "#64f939"
  },
  {
    "tribeId": 100472,
    "color": "#6c88d3"
  },
  {
    "tribeId": 100475,
    "color": "#aa55b1"
  }
]