[
  {
    "tribeId": 100038,
    "color": "#a4af15"
  },
  {
    "tribeId": 100328,
    "color": "#2c7630"
  },
  {
    "tribeId": 100205,
    "color": "#593315"
  },
  {
    "tribeId": 100249,
    "color": "#f4c800"
  },
  {
    "tribeId": 1000076,
    "color": "#472d1d"
  },
  {
    "tribeId": 100167,
    "color": "#c10020"
  },
  {
    "tribeId": 100195,
    "color": "#ffb300"
  },
  {
    "tribeId": 100025,
    "color": "#ff8e00"
  },
  {
    "tribeId": 100061,
    "color": "#a6bdd7"
  },
  {
    "tribeId": 1000024,
    "color": "#f9cb27"
  },
  {
    "tribeId": 100371,
    "color": "#86a8f2"
  },
  {
    "tribeId": 100375,
    "color": "#00538a"
  },
  {
    "tribeId": 100048,
    "color": "#cea262"
  },
  {
    "tribeId": 100213,
    "color": "#f6768e"
  },
  {
    "tribeId": 1000063,
    "color": "#29deb6"
  },
  {
    "tribeId": 100190,
    "color": "#007d34"
  },
  {
    "tribeId": 100364,
    "color": "#cbb8bc"
  },
  {
    "tribeId": 100293,
    "color": "#232c16"
  },
  {
    "tribeId": 100351,
    "color": "#1c9383"
  },
  {
    "tribeId": 100241,
    "color": "#d6bfc8"
  },
  {
    "tribeId": 1000066,
    "color": "#90953e"
  },
  {
    "tribeId": 100272,
    "color": "#824bbc"
  },
  {
    "tribeId": 100308,
    "color": "#ad3bae"
  },
  {
    "tribeId": 100372,
    "color": "#88a0d3"
  },
  {
    "tribeId": 100245,
    "color": "#bb507d"
  },
  {
    "tribeId": 100153,
    "color": "#baf765"
  },
  {
    "tribeId": 100174,
    "color": "#8f165d"
  },
  {
    "tribeId": 1000029,
    "color": "#f04296"
  },
  {
    "tribeId": 100002,
    "color": "#803e75"
  },
  {
    "tribeId": 100280,
    "color": "#b32851"
  },
  {
    "tribeId": 100327,
    "color": "#4d05c9"
  },
  {
    "tribeId": 100233,
    "color": "#30871c"
  },
  {
    "tribeId": 100266,
    "color": "#9055b6"
  },
  {
    "tribeId": 100478,
    "color": "#67b596"
  },
  {
    "tribeId": 100254,
    "color": "#dd777f"
  },
  {
    "tribeId": 100358,
    "color": "#6ad76c"
  },
  {
    "tribeId": 100054,
    "color": "#ff6800"
  },
  {
    "tribeId": 100279,
    "color": "#43a03d"
  },
  {
    "tribeId": 100134,
    "color": "#f13a13"
  },
  {
    "tribeId": 100429,
    "color": "#e21068"
  },
  {
    "tribeId": 1000051,
    "color": "#3f609b"
  },
  {
    "tribeId": 100165,
    "color": "#1e46a8"
  },
  {
    "tribeId": 100094,
    "color": "#6a9e52"
  },
  {
    "tribeId": 1000019,
    "color": "#a73446"
  },
  {
    "tribeId": 100218,
    "color": "#f27db2"
  },
  {
    "tribeId": 100138,
    "color": "#92f64b"
  },
  {
    "tribeId": 100187,
    "color": "#1c5499"
  },
  {
    "tribeId": 100180,
    "color": "#e5db80"
  },
  {
    "tribeId": 100432,
    "color": "#e4253d"
  },
  {
    "tribeId": 1000031,
    "color": "#efada0"
  },
  {
    "tribeId": 100318,
    "color": "#586af4"
  },
  {
    "tribeId": 100314,
    "color": "#61f027"
  },
  {
    "tribeId": 100219,
    "color": "#7f720e"
  },
  {
    "tribeId": 100136,
    "color": "#0dfb17"
  },
  {
    "tribeId": 100306,
    "color": "#443642"
  },
  {
    "tribeId": 100476,
    "color": "#39775a"
  },
  {
    "tribeId": 100452,
    "color": "#b8b0a9"
  },
  {
    "tribeId": 100442,
    "color": "#f1c5ba"
  },
  {
    "tribeId": 100415,
    "color": "#cd5883"
  },
  {
    "tribeId": 100179,
    "color": "#1a3820"
  },
  {
    "tribeId": 100192,
    "color": "#6b79f0"
  },
  {
    "tribeId": 100224,
    "color": "#b04fc9"
  },
  {
    "tribeId": 100394,
    "color": "#51918c"
  },
  {
    "tribeId": 1000047,
    "color": "#8b1283"
  },
  {
    "tribeId": 100216,
    "color": "#93aa00"
  },
  {
    "tribeId": 1000023,
    "color": "#3c0e57"
  },
  {
    "tribeId": 100325,
    "color": "#82a0a5"
  },
  {
    "tribeId": 100399,
    "color": "#3dabac"
  },
  {
    "tribeId": 100256,
    "color": "#e136fb"
  },
  {
    "tribeId": 100013,
    "color": "#53377a"
  },
  {
    "tribeId": 100386,
    "color": "#f666a3"
  },
  {
    "tribeId": 1000053,
    "color": "#399297"
  },
  {
    "tribeId": 100210,
    "color": "#a26439"
  },
  {
    "tribeId": 100244,
    "color": "#eca182"
  },
  {
    "tribeId": 100008,
    "color": "#2592e5"
  },
  {
    "tribeId": 100261,
    "color": "#77e6e5"
  },
  {
    "tribeId": 100477,
    "color": "#cd2d9d"
  },
  {
    "tribeId": 100292,
    "color": "#25b4b6"
  },
  {
    "tribeId": 100191,
    "color": "#634bb7"
  },
  {
    "tribeId": 100122,
    "color": "#dddc8c"
  },
  {
    "tribeId": 100235,
    "color": "#738842"
  },
  {
    "tribeId": 100162,
    "color": "#f3b9e7"
  },
  {
    "tribeId": 100234,
    "color": "#2517fd"
  },
  {
    "tribeId": 100252,
    "color": "#f3e8ac"
  },
  {
    "tribeId": 100264,
    "color": "#4a4e6c"
  },
  {
    "tribeId": 100298,
    "color": "#d45c0e"
  },
  {
    "tribeId": 100288,
    "color": "#bec4c4"
  },
  {
    "tribeId": 100246,
    "color": "#c61409"
  },
  {
    "tribeId": 100076,
    "color": "#5ed0b0"
  },
  {
    "tribeId": 100081,
    "color": "#ebd546"
  },
  {
    "tribeId": 100156,
    "color": "#dfc487"
  },
  {
    "tribeId": 100437,
    "color": "#ac7919"
  },
  {
    "tribeId": 100355,
    "color": "#3f31d8"
  },
  {
    "tribeId": 100290,
    "color": "#fc51ce"
  },
  {
    "tribeId": 100380,
    "color": "#e6d843"
  },
  {
    "tribeId": 100104,
    "color": "#f0da65"
  },
  {
    "tribeId": 100253,
    "color": "#4a8eee"
  },
  {
    "tribeId": 100250,
    "color": "#817066"
  },
  {
    "tribeId": 1000065,
    "color": "#a81e17"
  },
  {
    "tribeId": 100178,
    "color": "#c7ac74"
  },
  {
    "tribeId": 100058,
    "color": "#ff7a5c"
  },
  {
    "tribeId": 100177,
    "color": "#3995e7"
  },
  {
    "tribeId": 100356,
    "color": "#373941"
  },
  {
    "tribeId": 100140,
    "color": "#b61424"
  },
  {
    "tribeId": 100077,
    "color": "#249dd4"
  },
  {
    "tribeId": 1000025,
    "color": "#52942a"
  },
  {
    "tribeId": 1000059,
    "color": "#34c072"
  },
  {
    "tribeId": 100160,
    "color": "#f4de3a"
  },
  {
    "tribeId": 100171,
    "color": "#c56cf4"
  },
  {
    "tribeId": 100036,
    "color": "#4aa147"
  },
  {
    "tribeId": 100366,
    "color": "#5736a5"
  },
  {
    "tribeId": 100295,
    "color": "#70e3cc"
  },
  {
    "tribeId": 100275,
    "color": "#a3069b"
  },
  {
    "tribeId": 100400,
    "color": "#efc518"
  },
  {
    "tribeId": 100222,
    "color": "#8c30c4"
  },
  {
    "tribeId": 100066,
    "color": "#1ecb3d"
  },
  {
    "tribeId": 100024,
    "color": "#90f6f8"
  },
  {
    "tribeId": 100350,
    "color": "#c3745c"
  },
  {
    "tribeId": 1000041,
    "color": "#a3d1cd"
  },
  {
    "tribeId": 100278,
    "color": "#3a7328"
  },
  {
    "tribeId": 100406,
    "color": "#f2ec96"
  },
  {
    "tribeId": 100062,
    "color": "#f95fdd"
  },
  {
    "tribeId": 1000075,
    "color": "#7db3b8"
  },
  {
    "tribeId": 1000054,
    "color": "#07ad8e"
  },
  {
    "tribeId": 100349,
    "color": "#8e44fa"
  },
  {
    "tribeId": 100363,
    "color": "#5a67ad"
  },
  {
    "tribeId": 100123,
    "color": "#7f180d"
  },
  {
    "tribeId": 100073,
    "color": "#74a69f"
  },
  {
    "tribeId": 100240,
    "color": "#b7b8a9"
  },
  {
    "tribeId": 100142,
    "color": "#4d92c0"
  },
  {
    "tribeId": 100347,
    "color": "#49cc12"
  },
  {
    "tribeId": 100017,
    "color": "#fe6992"
  },
  {
    "tribeId": 100112,
    "color": "#72fcd8"
  },
  {
    "tribeId": 1000014,
    "color": "#8092cf"
  },
  {
    "tribeId": 100259,
    "color": "#e6a018"
  },
  {
    "tribeId": 100427,
    "color": "#848848"
  },
  {
    "tribeId": 100135,
    "color": "#6a3530"
  },
  {
    "tribeId": 100125,
    "color": "#60496a"
  },
  {
    "tribeId": 100060,
    "color": "#1fc4cc"
  },
  {
    "tribeId": 100316,
    "color": "#883a33"
  },
  {
    "tribeId": 100168,
    "color": "#ecaccb"
  },
  {
    "tribeId": 100087,
    "color": "#1c34e6"
  },
  {
    "tribeId": 100004,
    "color": "#a60844"
  },
  {
    "tribeId": 100031,
    "color": "#fb1c46"
  },
  {
    "tribeId": 100354,
    "color": "#22d8d4"
  },
  {
    "tribeId": 100258,
    "color": "#dd8d05"
  },
  {
    "tribeId": 100346,
    "color": "#87322f"
  },
  {
    "tribeId": 100396,
    "color": "#60e25d"
  },
  {
    "tribeId": 100342,
    "color": "#90e782"
  },
  {
    "tribeId": 100132,
    "color": "#a6dfa4"
  },
  {
    "tribeId": 100211,
    "color": "#c5e9c1"
  },
  {
    "tribeId": 100052,
    "color": "#a493e4"
  },
  {
    "tribeId": 100487,
    "color": "#04c96c"
  },
  {
    "tribeId": 100018,
    "color": "#31dd80"
  },
  {
    "tribeId": 100080,
    "color": "#046e18"
  },
  {
    "tribeId": 100044,
    "color": "#e83e6f"
  },
  {
    "tribeId": 100370,
    "color": "#944037"
  },
  {
    "tribeId": 100383,
    "color": "#c60008"
  },
  {
    "tribeId": 100281,
    "color": "#038bc9"
  },
  {
    "tribeId": 100078,
    "color": "#6e8a4b"
  },
  {
    "tribeId": 100009,
    "color": "#63fe27"
  },
  {
    "tribeId": 1000020,
    "color": "#9f3632"
  },
  {
    "tribeId": 100046,
    "color": "#847c44"
  },
  {
    "tribeId": 100286,
    "color": "#eed9c2"
  },
  {
    "tribeId": 100304,
    "color": "#985654"
  },
  {
    "tribeId": 100221,
    "color": "#ae5c73"
  },
  {
    "tribeId": 100200,
    "color": "#44a7a9"
  },
  {
    "tribeId": 100384,
    "color": "#13129e"
  },
  {
    "tribeId": 1000056,
    "color": "#6dfde8"
  },
  {
    "tribeId": 100032,
    "color": "#b9a107"
  },
  {
    "tribeId": 100248,
    "color": "#1b943f"
  },
  {
    "tribeId": 100227,
    "color": "#20ccde"
  },
  {
    "tribeId": 100289,
    "color": "#586438"
  },
  {
    "tribeId": 100373,
    "color": "#e563c0"
  },
  {
    "tribeId": 100014,
    "color": "#2aa466"
  },
  {
    "tribeId": 100064,
    "color": "#732da9"
  },
  {
    "tribeId": 100409,
    "color": "#b2542f"
  },
  {
    "tribeId": 1000058,
    "color": "#5529e2"
  },
  {
    "tribeId": 100193,
    "color": "#a050eb"
  },
  {
    "tribeId": 100063,
    "color": "#883237"
  },
  {
    "tribeId": 100348,
    "color": "#48cada"
  },
  {
    "tribeId": 100368,
    "color": "#3dd344"
  },
  {
    "tribeId": 100117,
    "color": "#837888"
  },
  {
    "tribeId": 100095,
    "color": "#7555f6"
  },
  {
    "tribeId": 100128,
    "color": "#3b5e43"
  },
  {
    "tribeId": 100488,
    "color": "#e7e76c"
  },
  {
    "tribeId": 100340,
    "color": "#37f8d0"
  },
  {
    "tribeId": 1000036,
    "color": "#3e064c"
  },
  {
    "tribeId": 100106,
    "color": "#d7c56b"
  },
  {
    "tribeId": 100184,
    "color": "#5b7f7c"
  },
  {
    "tribeId": 100451,
    "color": "#f1cf32"
  },
  {
    "tribeId": 100172,
    "color": "#009c98"
  },
  {
    "tribeId": 1000073,
    "color": "#e5ecd0"
  },
  {
    "tribeId": 100239,
    "color": "#22eeb4"
  },
  {
    "tribeId": 100291,
    "color": "#213dfe"
  },
  {
    "tribeId": 100035,
    "color": "#3719ca"
  },
  {
    "tribeId": 1000069,
    "color": "#9eb768"
  },
  {
    "tribeId": 100455,
    "color": "#7e5038"
  },
  {
    "tribeId": 100139,
    "color": "#6509c3"
  },
  {
    "tribeId": 100336,
    "color": "#8d650e"
  },
  {
    "tribeId": 100411,
    "color": "#d727f7"
  },
  {
    "tribeId": 100242,
    "color": "#0b8285"
  },
  {
    "tribeId": 100148,
    "color": "#c43ac0"
  },
  {
    "tribeId": 100145,
    "color": "#aa02f9"
  },
  {
    "tribeId": 100466,
    "color": "#9b140a"
  },
  {
    "tribeId": 100334,
    "color": "#1c1dc7"
  },
  {
    "tribeId": 100322,
    "color": "#4d9fab"
  },
  {
    "tribeId": 100057,
    "color": "#a0bcc6"
  },
  {
    "tribeId": 100051,
    "color": "#14727e"
  },
  {
    "tribeId": 100482,
    "color": "#f89a92"
  },
  {
    "tribeId": 100268,
    "color": "#d35887"
  },
  {
    "tribeId": 1000078,
    "color": "#c24ac6"
  },
  {
    "tribeId": 100204,
    "color": "#bb15b9"
  },
  {
    "tribeId": 100317,
    "color": "#7871dd"
  },
  {
    "tribeId": 100407,
    "color": "#09f2b5"
  },
  {
    "tribeId": 100282,
    "color": "#6de23c"
  },
  {
    "tribeId": 100486,
    "color": "#2e48eb"
  },
  {
    "tribeId": 100301,
    "color": "#fa40c4"
  },
  {
    "tribeId": 1000084,
    "color": "#61376a"
  },
  {
    "tribeId": 100362,
    "color": "#31f610"
  },
  {
    "tribeId": 100311,
    "color": "#07cb9f"
  },
  {
    "tribeId": 100126,
    "color": "#2dd5a8"
  },
  {
    "tribeId": 100357,
    "color": "#72d8c9"
  },
  {
    "tribeId": 1000060,
    "color": "#426008"
  },
  {
    "tribeId": 100161,
    "color": "#0ed32d"
  },
  {
    "tribeId": 100294,
    "color": "#cc96c8"
  },
  {
    "tribeId": 100446,
    "color": "#10a68f"
  },
  {
    "tribeId": 100393,
    "color": "#42ca51"
  },
  {
    "tribeId": 100209,
    "color": "#a6d717"
  },
  {
    "tribeId": 1000062,
    "color": "#c16013"
  },
  {
    "tribeId": 1000055,
    "color": "#5c891e"
  },
  {
    "tribeId": 100223,
    "color": "#a971a5"
  },
  {
    "tribeId": 1000026,
    "color": "#3edb1d"
  },
  {
    "tribeId": 100214,
    "color": "#0cf90a"
  },
  {
    "tribeId": 100196,
    "color": "#71ebe7"
  },
  {
    "tribeId": 100232,
    "color": "#e2ec6b"
  },
  {
    "tribeId": 100181,
    "color": "#96939f"
  },
  {
    "tribeId": 100439,
    "color": "#a0204f"
  },
  {
    "tribeId": 100391,
    "color": "#7fc400"
  },
  {
    "tribeId": 100436,
    "color": "#4d85fd"
  },
  {
    "tribeId": 100320,
    "color": "#90af77"
  },
  {
    "tribeId": 100472,
    "color": "#b6e4d5"
  },
  {
    "tribeId": 100475,
    "color": "#e96361"
  }
]